{"title":"聰明人和儍子和奴才","work":"野草","tokens":[[{"t":"奴才","d":0},{"t":"總","l":"3","s":"总","d":1},{"t":"不過","l":"2","s":"不过","d":2},{"t":"是","l":"1","d":3},{"t":"尋","l":"7-9","s":"寻","d":4},{"t":"人","l":"1","d":5},{"t":"訴苦","l":"7-9","s":"诉苦","d":6},{"t":"。"},{"t":"只要","l":"2","d":7},{"t":"這樣","l":"2","s":"这样","d":8},{"t":"，"},{"t":"也","l":"1","d":9},{"t":"只能","l":"2","d":10},{"t":"這樣","l":"2","s":"这样","d":8},{"t":"。"},{"t":"有","l":"1","d":11},{"t":"一","l":"1","d":12},{"t":"日","l":"1","d":13},{"t":"，"},{"t":"他","l":"1","d":14},{"t":"遇到","l":"4","d":15},{"t":"一個","s":"一个","d":16},{"t":"聰明","l":"5","s":"聪明","d":17},{"t":"人","l":"1","d":5},{"t":"。"}],[{"t":"『"},{"t":"先生","l":"1","d":18},{"t":"！』"},{"t":"他","l":"1","d":14},{"t":"悲哀","l":"7-9","d":19},{"t":"地","l":"1","d":20},{"t":"說","l":"1","s":"说","d":21},{"t":"，"},{"t":"眼淚","l":"4","s":"眼泪","d":22},{"t":"聯","s":"联","d":23},{"t":"成","l":"2","d":24},{"t":"一線","l":"7-9","s":"一线","d":25},{"t":"，"},{"t":"就","l":"1","d":26},{"t":"從","l":"1","s":"从","d":27},{"t":"眼角","d":28},{"t":"上","l":"1","d":29},{"t":"直流","d":30},{"t":"下來","l":"3","s":"下来","d":31},{"t":"。『"},{"t":"你","l":"1","d":32},{"t":"知道","l":"1","d":33},{"t":"的","l":"1","d":34},{"t":"。"},{"t":"我","l":"1","d":35},{"t":"所","l":"3","d":36},{"t":"過","l":"1","s":"过","d":37},{"t":"的","l":"1","d":34},{"t":"簡直","l":"3","s":"简直","d":38},{"t":"不是","d":39},{"t":"人","l":"1","d":5},{"t":"的","l":"1","d":34},{"t":"生活","l":"2","d":40},{"t":"。"},{"t":"喫","s":"吃","d":41},{"t":"的","l":"1","d":34},{"t":"是","l":"1","d":3},{"t":"一","l":"1","d":12},{"t":"天","l":"1","d":42},{"t":"未必","l":"4","d":43},{"t":"有","l":"1","d":11},{"t":"一","l":"1","d":12},{"t":"餐","l":"6","d":44},{"t":"，"},{"t":"這","l":"1","s":"这","d":45},{"t":"一","l":"1","d":12},{"t":"餐","l":"6","d":44},{"t":"又","l":"2","d":46},{"t":"不過","l":"2","s":"不过","d":2},{"t":"是","l":"1","d":3},{"t":"高粱","d":47},{"t":"皮","l":"3","d":48},{"t":"，"},{"t":"連","l":"3","s":"连","d":49},{"t":"豬狗","s":"猪狗","d":50},{"t":"都","l":"1","d":51},{"t":"不要","l":"2","d":52},{"t":"喫","s":"吃","d":41},{"t":"的","l":"1","d":34},{"t":"，"},{"t":"尙","d":53},{"t":"且","l":"7-9","d":54},{"t":"只有","l":"3","d":55},{"t":"一","l":"1","d":12},{"t":"小","l":"1","d":56},{"t":"碗","l":"2","d":57},{"t":"……。』"}],[{"t":"『"},{"t":"這","l":"1","s":"这","d":45},{"t":"實","s":"实","d":58},{"t":"令人","d":59},{"t":"同情","l":"4","d":60},{"t":"。』"},{"t":"聰明","l":"5","s":"聪明","d":17},{"t":"人","l":"1","d":5},{"t":"也","l":"1","d":9},{"t":"慘然","s":"惨然","d":61},{"t":"說","l":"1","s":"说","d":21},{"t":"。"}],[{"t":"『"},{"t":"可不是","l":"7-9","d":62},{"t":"麽","s":"么","d":63},{"t":"！』"},{"t":"他","l":"1","d":14},{"t":"高興","l":"1","s":"高兴","d":64},{"t":"了","l":"1","d":65},{"t":"。『"},{"t":"可是","l":"2","d":66},{"t":"做工","d":67},{"t":"是","l":"1","d":3},{"t":"晝夜","l":"7-9","s":"昼夜","d":68},{"t":"無","l":"4","s":"无","d":69},{"t":"休息","l":"1","d":70},{"t":"的","l":"1","d":34},{"t":"："},{"t":"淸","d":71},{"t":"早","l":"1","d":72},{"t":"擔","l":"7-9","s":"担","d":73},{"t":"水","l":"1","d":74},{"t":"晚","l":"1","d":75},{"t":"燒","l":"4","s":"烧","d":76},{"t":"飯","l":"1","s":"饭","d":77},{"t":"，"},{"t":"上午","l":"1","d":78},{"t":"跑","l":"1","d":79},{"t":"街","l":"2","d":80},{"t":"夜","l":"2","d":81},{"t":"磨","l":"6","d":82},{"t":"麫","s":"面","d":83},{"t":"，"},{"t":"晴","l":"2","d":84},{"t":"洗衣","d":85},{"t":"裳","d":86},{"t":"雨","l":"1","d":87},{"t":"張","l":"3","s":"张","d":88},{"t":"傘","l":"4","s":"伞","d":89},{"t":"，"},{"t":"冬","d":90},{"t":"燒","l":"4","s":"烧","d":76},{"t":"汽","d":91},{"t":"鑪","s":"𬬻","d":92},{"t":"夏","d":93},{"t":"打","l":"1","d":94},{"t":"扇","l":"5","d":95},{"t":"。"},{"t":"半夜","l":"2","d":96},{"t":"要","l":"1","d":97},{"t":"煨","d":98},{"t":"銀耳","s":"银耳","d":99},{"t":"，"},{"t":"侍候","l":"7-9","d":100},{"t":"主人","l":"2","d":101},{"t":"耍錢","s":"耍钱","d":102},{"t":"；"},{"t":"頭","l":"2","s":"头","d":103},{"t":"錢","l":"1","s":"钱","d":104},{"t":"從來沒","s":"从来没","d":105},{"t":"分","l":"1","d":106},{"t":"，"},{"t":"有時","l":"1","s":"有时","d":107},{"t":"還","l":"1","s":"还","d":108},{"t":"挨","l":"6","d":109},{"t":"皮鞭","d":110},{"t":"……。』"}],[{"t":"『"},{"t":"唉唉","d":111},{"t":"……。』"},{"t":"聰明","l":"5","s":"聪明","d":17},{"t":"人","l":"1","d":5},{"t":"歎","s":"叹","d":112},{"t":"息","d":113},{"t":"着","l":"1","d":114},{"t":"，"},{"t":"眼圈","d":115},{"t":"有些","d":116},{"t":"發紅","s":"发红","d":117},{"t":"，"},{"t":"似乎","l":"4","d":118},{"t":"要","l":"1","d":97},{"t":"下","l":"1","d":119},{"t":"淚","l":"4","s":"泪","d":120},{"t":"。"}],[{"t":"『"},{"t":"先生","l":"1","d":18},{"t":"！"},{"t":"我","l":"1","d":35},{"t":"這樣","l":"2","s":"这样","d":8},{"t":"是","l":"1","d":3},{"t":"敷衍","d":121},{"t":"不下","d":122},{"t":"去","l":"1","d":123},{"t":"的","l":"1","d":34},{"t":"。"},{"t":"我","l":"1","d":35},{"t":"總得","s":"总得","d":124},{"t":"另外","l":"3","d":125},{"t":"想法","l":"2","d":126},{"t":"子","d":127},{"t":"。"},{"t":"可是","l":"2","d":66},{"t":"什","d":128},{"t":"麽","s":"么","d":63},{"t":"法子","d":129},{"t":"呢","l":"1","d":130},{"t":"？…… 』"}],[{"t":"『"},{"t":"我","l":"1","d":35},{"t":"想","l":"1","d":131},{"t":"，"},{"t":"你","l":"1","d":32},{"t":"總","l":"3","s":"总","d":1},{"t":"會","l":"1","s":"会","d":132},{"t":"好起來","s":"好起来","d":133},{"t":"……。』"}],[{"t":"『"},{"t":"是","l":"1","d":3},{"t":"麽","s":"么","d":63},{"t":"？"},{"t":"但願如此","s":"但愿如此","d":134},{"t":"。"},{"t":"可是","l":"2","d":66},{"t":"我","l":"1","d":35},{"t":"對","l":"1","s":"对","d":135},{"t":"先生","l":"1","d":18},{"t":"訴","s":"诉","d":136},{"t":"了","l":"1","d":65},{"t":"寃","d":137},{"t":"苦","l":"4","d":138},{"t":"，"},{"t":"又","l":"2","d":46},{"t":"得","l":"2","d":139},{"t":"你","l":"1","d":32},{"t":"的","l":"1","d":34},{"t":"同情","l":"4","d":60},{"t":"和","l":"1","d":140},{"t":"慰","d":141},{"t":"安","l":"4","d":142},{"t":"，"},{"t":"已經","l":"2","s":"已经","d":143},{"t":"舒坦","d":144},{"t":"得","l":"2","d":139},{"t":"不少","l":"2","d":145},{"t":"了","l":"1","d":65},{"t":"。"},{"t":"可見","l":"4","s":"可见","d":146},{"t":"天理","d":147},{"t":"沒有","l":"1","s":"没有","d":148},{"t":"滅絕","l":"7-9","s":"灭绝","d":149},{"t":"……。』"}],[{"t":"但是","l":"2","d":150},{"t":"，"},{"t":"不","l":"1","d":151},{"t":"幾","l":"1","s":"几","d":152},{"t":"日","l":"1","d":13},{"t":"，"},{"t":"他","l":"1","d":14},{"t":"又","l":"2","d":46},{"t":"不平","l":"7-9","d":153},{"t":"起來","l":"1","s":"起来","d":154},{"t":"了","l":"1","d":65},{"t":"，"},{"t":"仍然","l":"3","d":155},{"t":"尋","l":"7-9","s":"寻","d":4},{"t":"人","l":"1","d":5},{"t":"去","l":"1","d":123},{"t":"訴苦","l":"7-9","s":"诉苦","d":6},{"t":"。"}],[{"t":"『"},{"t":"先生","l":"1","d":18},{"t":"！ 』"},{"t":"他","l":"1","d":14},{"t":"流","l":"2","d":156},{"t":"着眼","l":"7-9","d":157},{"t":"淚","l":"4","s":"泪","d":120},{"t":"說","l":"1","s":"说","d":21},{"t":"，『"},{"t":"你","l":"1","d":32},{"t":"知道","l":"1","d":33},{"t":"的","l":"1","d":34},{"t":"。"},{"t":"我","l":"1","d":35},{"t":"住","l":"1","d":158},{"t":"的","l":"1","d":34},{"t":"簡直","l":"3","s":"简直","d":38},{"t":"比","l":"1","d":159},{"t":"豬","l":"3","s":"猪","d":160},{"t":"窼"},{"t":"還不如","s":"还不如","d":161},{"t":"。"},{"t":"主人","l":"2","d":101},{"t":"並不","s":"并不","d":162},{"t":"將","l":"5","s":"将","d":163},{"t":"我","l":"1","d":35},{"t":"當","l":"2","s":"当","d":164},{"t":"人","l":"1","d":5},{"t":"；"},{"t":"他","l":"1","d":14},{"t":"對","l":"1","s":"对","d":135},{"t":"他","l":"1","d":14},{"t":"的","l":"1","d":34},{"t":"叭","d":165},{"t":"兒","s":"儿","d":166},{"t":"狗","l":"2","d":167},{"t":"還","l":"1","s":"还","d":108},{"t":"要好","l":"6","d":168},{"t":"到","l":"1","d":169},{"t":"幾","l":"1","s":"几","d":152},{"t":"萬","l":"2","s":"万","d":170},{"t":"倍","l":"4","d":171},{"t":"……。』"}],[{"t":"『"},{"t":"混","l":"6","d":172},{"t":"帳","s":"帐","d":173},{"t":"！ 』"},{"t":"那","l":"1","d":174},{"t":"人大","d":175},{"t":"叫","l":"1","d":176},{"t":"起來","l":"1","s":"起来","d":154},{"t":"，"},{"t":"使","l":"3","d":177},{"t":"他","l":"1","d":14},{"t":"喫","s":"吃","d":41},{"t":"驚","l":"7-9","s":"惊","d":178},{"t":"了","l":"1","d":65},{"t":"。"},{"t":"那","l":"1","d":174},{"t":"人","l":"1","d":5},{"t":"是","l":"1","d":3},{"t":"一個","s":"一个","d":16},{"t":"儍","d":179},{"t":"子","d":127},{"t":"。"}],[{"t":"『"},{"t":"先生","l":"1","d":18},{"t":"，"},{"t":"我","l":"1","d":35},{"t":"住","l":"1","d":158},{"t":"的","l":"1","d":34},{"t":"只是","l":"3","d":180},{"t":"一","l":"1","d":12},{"t":"間","l":"1","s":"间","d":181},{"t":"破","l":"3","d":182},{"t":"小屋","d":183},{"t":"，"},{"t":"又","l":"2","d":46},{"t":"溼","s":"湿","d":184},{"t":"，"},{"t":"又","l":"2","d":46},{"t":"陰","l":"2","s":"阴","d":185},{"t":"，"},{"t":"滿","l":"2","s":"满","d":186},{"t":"是","l":"1","d":3},{"t":"臭蟲","s":"臭虫","d":187},{"t":"，"},{"t":"睡","l":"1","d":188},{"t":"下去","l":"3","d":189},{"t":"就","l":"1","d":26},{"t":"咬","l":"5","d":190},{"t":"得","l":"2","d":139},{"t":"眞","s":"真","d":191},{"t":"可以","l":"2","d":192},{"t":"。"},{"t":"穢","s":"秽","d":193},{"t":"氣","l":"2","s":"气","d":194},{"t":"衝","l":"4","s":"冲","d":195},{"t":"着","l":"1","d":114},{"t":"鼻子","l":"5","d":196},{"t":"，"},{"t":"四面","d":197},{"t":"又","l":"2","d":46},{"t":"沒有","l":"1","s":"没有","d":148},{"t":"一個","s":"一个","d":16},{"t":"窗","d":198},{"t":"……。』"}],[{"t":"『"},{"t":"你","l":"1","d":32},{"t":"不會","s":"不会","d":199},{"t":"要","l":"1","d":97},{"t":"你","l":"1","d":32},{"t":"的","l":"1","d":34},{"t":"主人","l":"2","d":101},{"t":"開","l":"1","s":"开","d":200},{"t":"一個","s":"一个","d":16},{"t":"窗","d":198},{"t":"的","l":"1","d":34},{"t":"麽","s":"么","d":63},{"t":"？ 』"}],[{"t":"『"},{"t":"這","l":"1","s":"这","d":45},{"t":"怎麽","s":"怎么","d":201},{"t":"行","l":"1","d":202},{"t":"？…… 』"}],[{"t":"『"},{"t":"那麽","s":"那么","d":203},{"t":"，"},{"t":"你","l":"1","d":32},{"t":"帶","l":"2","s":"带","d":204},{"t":"我去","d":205},{"t":"看","l":"1","d":206},{"t":"去","l":"1","d":123},{"t":"！ 』"}],[{"t":"儍","d":179},{"t":"子","d":127},{"t":"跟","l":"1","d":207},{"t":"奴才","d":0},{"t":"到","l":"1","d":169},{"t":"他","l":"1","d":14},{"t":"屋外","d":208},{"t":"，"},{"t":"動手","l":"5","s":"动手","d":209},{"t":"就","l":"1","d":26},{"t":"砸","l":"7-9","d":210},{"t":"那","l":"1","d":174},{"t":"泥","l":"6","d":211},{"t":"牆","l":"2","s":"墙","d":212},{"t":"。"}],[{"t":"『"},{"t":"先生","l":"1","d":18},{"t":"！"},{"t":"你","l":"1","d":32},{"t":"幹","l":"1","s":"干","d":213},{"t":"什","d":128},{"t":"麽","s":"么","d":63},{"t":"？ 』"},{"t":"他","l":"1","d":14},{"t":"大驚","s":"大惊","d":214},{"t":"地","l":"1","d":20},{"t":"說","l":"1","s":"说","d":21},{"t":"。"}],[{"t":"『"},{"t":"我","l":"1","d":35},{"t":"給","l":"1","s":"给","d":215},{"t":"你","l":"1","d":32},{"t":"打開","l":"1","s":"打开","d":216},{"t":"一個","s":"一个","d":16},{"t":"窗","d":198},{"t":"洞","l":"5","d":217},{"t":"來","l":"1","s":"来","d":218},{"t":"。 』"}],[{"t":"『"},{"t":"這不","s":"这不","d":219},{"t":"行","l":"1","d":202},{"t":"！"},{"t":"主人","l":"2","d":101},{"t":"要","l":"1","d":97},{"t":"罵","l":"5","s":"骂","d":220},{"t":"的","l":"1","d":34},{"t":"！ 』"}],[{"t":"『"},{"t":"管他呢","d":221},{"t":"！ 』"},{"t":"他","l":"1","d":14},{"t":"仍然","l":"3","d":155},{"t":"砸","l":"7-9","d":210},{"t":"。"}],[{"t":"『"},{"t":"人","l":"1","d":5},{"t":"來","l":"1","s":"来","d":218},{"t":"呀","l":"4","d":222},{"t":"！"},{"t":"強盜","l":"6","s":"强盗","d":223},{"t":"在","l":"1","d":224},{"t":"毀","l":"6","s":"毁","d":225},{"t":"咱們","l":"2","s":"咱们","d":226},{"t":"的","l":"1","d":34},{"t":"屋子","l":"3","d":227},{"t":"了","l":"1","d":65},{"t":"！"},{"t":"快","l":"1","d":228},{"t":"來","l":"1","s":"来","d":218},{"t":"呀","l":"4","d":222},{"t":"！"},{"t":"遲","l":"5","s":"迟","d":229},{"t":"一點","s":"一点","d":230},{"t":"可","l":"5","d":231},{"t":"要","l":"1","d":97},{"t":"打","l":"1","d":94},{"t":"出","l":"1","d":232},{"t":"窟窿","l":"7-9","d":233},{"t":"來","l":"1","s":"来","d":218},{"t":"了","l":"1","d":65},{"t":"！…… 』"},{"t":"他","l":"1","d":14},{"t":"哭","l":"2","d":234},{"t":"嚷","l":"7-9","d":235},{"t":"着","l":"1","d":114},{"t":"，"},{"t":"在地","d":236},{"t":"上","l":"1","d":29},{"t":"團","l":"3","s":"团","d":237},{"t":"團","l":"3","s":"团","d":237},{"t":"地","l":"1","d":20},{"t":"打滾","s":"打滚","d":238},{"t":"。"}],[{"t":"一","l":"1","d":12},{"t":"羣","s":"群","d":239},{"t":"奴才","d":0},{"t":"都","l":"1","d":51},{"t":"出來","l":"1","s":"出来","d":240},{"t":"了","l":"1","d":65},{"t":"，"},{"t":"將","l":"5","s":"将","d":163},{"t":"儍","d":179},{"t":"子","d":127},{"t":"趕走","s":"赶走","d":241},{"t":"。"}],[{"t":"聽到","l":"1","s":"听到","d":242},{"t":"了","l":"1","d":65},{"t":"喊聲","s":"喊声","d":243},{"t":"，"},{"t":"慢慢","l":"3","d":244},{"t":"地","l":"1","d":20},{"t":"最後","l":"1","s":"最后","d":245},{"t":"出來","l":"1","s":"出来","d":240},{"t":"的","l":"1","d":34},{"t":"是","l":"1","d":3},{"t":"主人","l":"2","d":101},{"t":"。"}],[{"t":"『"},{"t":"有","l":"1","d":11},{"t":"強盜","l":"6","s":"强盗","d":223},{"t":"要","l":"1","d":97},{"t":"來","l":"1","s":"来","d":218},{"t":"毀","l":"6","s":"毁","d":225},{"t":"咱們","l":"2","s":"咱们","d":226},{"t":"的","l":"1","d":34},{"t":"屋子","l":"3","d":227},{"t":"，"},{"t":"我","l":"1","d":35},{"t":"首先","l":"3","d":246},{"t":"叫喊","d":247},{"t":"起來","l":"1","s":"起来","d":154},{"t":"，"},{"t":"大家","l":"2","d":248},{"t":"一同","l":"6","d":249},{"t":"把","l":"3","d":250},{"t":"他","l":"1","d":14},{"t":"趕走","s":"赶走","d":241},{"t":"了","l":"1","d":65},{"t":"。 』"},{"t":"他","l":"1","d":14},{"t":"恭敬","d":251},{"t":"而","l":"4","d":252},{"t":"得勝","s":"得胜","d":253},{"t":"地","l":"1","d":20},{"t":"說","l":"1","s":"说","d":21},{"t":"。"}],[{"t":"『"},{"t":"你","l":"1","d":32},{"t":"不錯","l":"2","s":"不错","d":254},{"t":"。』"},{"t":"主人","l":"2","d":101},{"t":"這樣","l":"2","s":"这样","d":8},{"t":"誇獎","l":"7-9","s":"夸奖","d":255},{"t":"他","l":"1","d":14},{"t":"。"}],[{"t":"這","l":"1","s":"这","d":45},{"t":"一","l":"1","d":12},{"t":"天","l":"1","d":42},{"t":"就","l":"1","d":26},{"t":"來","l":"1","s":"来","d":218},{"t":"了","l":"1","d":65},{"t":"許多","l":"2","s":"许多","d":256},{"t":"慰問","l":"5","s":"慰问","d":257},{"t":"的","l":"1","d":34},{"t":"人","l":"1","d":5},{"t":"，"},{"t":"聰明","l":"5","s":"聪明","d":17},{"t":"人","l":"1","d":5},{"t":"也","l":"1","d":9},{"t":"在內","l":"5","s":"在内","d":258},{"t":"。"}],[{"t":"『"},{"t":"先生","l":"1","d":18},{"t":"。"},{"t":"這","l":"1","s":"这","d":45},{"t":"回","l":"1","d":259},{"t":"因","l":"6","d":260},{"t":"爲","s":"为","d":261},{"t":"我","l":"1","d":35},{"t":"有","l":"1","d":11},{"t":"功","l":"7-9","d":262},{"t":"，"},{"t":"主人","l":"2","d":101},{"t":"誇獎","l":"7-9","s":"夸奖","d":255},{"t":"了","l":"1","d":65},{"t":"我","l":"1","d":35},{"t":"了","l":"1","d":65},{"t":"。"},{"t":"你","l":"1","d":32},{"t":"先前","l":"5","d":263},{"t":"說","l":"1","s":"说","d":21},{"t":"我","l":"1","d":35},{"t":"總","l":"3","s":"总","d":1},{"t":"會","l":"1","s":"会","d":132},{"t":"好起來","s":"好起来","d":133},{"t":"，"},{"t":"實在","l":"2","s":"实在","d":264},{"t":"是","l":"1","d":3},{"t":"有","l":"1","d":11},{"t":"先見之明","s":"先见之明","d":265},{"t":"……。』"},{"t":"他","l":"1","d":14},{"t":"大有希望","d":266},{"t":"似的","l":"4","d":267},{"t":"高興","l":"1","s":"高兴","d":64},{"t":"地","l":"1","d":20},{"t":"說","l":"1","s":"说","d":21},{"t":"。"}],[{"t":"『"},{"t":"可不是","l":"7-9","d":62},{"t":"嗎","l":"1","s":"吗","d":268},{"t":"……。』"},{"t":"聰明","l":"5","s":"聪明","d":17},{"t":"人","l":"1","d":5},{"t":"也","l":"1","d":9},{"t":"代","l":"3","d":269},{"t":"爲","s":"为","d":261},{"t":"高興","l":"1","s":"高兴","d":64},{"t":"似的","l":"4","d":267},{"t":"回答","l":"1","d":270},{"t":"他","l":"1","d":14},{"t":"。"}],[{"t":"（"},{"t":"一","l":"1","d":12},{"t":"九","l":"1","d":271},{"t":"二","l":"1","d":272},{"t":"五","l":"1","d":273},{"t":"年","l":"1","d":274},{"t":"十二月","d":275},{"t":"二十","d":276},{"t":"六","l":"1","d":277},{"t":"日","l":"1","d":13},{"t":"。）"}],[{"t":"1996"},{"t":"年","l":"1","d":274},{"t":"1"},{"t":"月","l":"1","d":278},{"t":"1"},{"t":"日","l":"1","d":13},{"t":"，"},{"t":"这","l":"1","d":279},{"t":"部","l":"3","d":280},{"t":"作品","l":"3","d":281},{"t":"在","l":"1","d":224},{"t":"原作","d":282},{"t":"國家","l":"1","s":"国家","d":283},{"t":"或","l":"2","d":284},{"t":"地區","l":"3","s":"地区","d":285},{"t":"屬於","l":"3","s":"属于","d":286},{"t":"公有","d":287},{"t":"領域","l":"7-9","s":"领域","d":288},{"t":"，"},{"t":"之前","l":"4","d":289},{"t":"在","l":"1","d":224},{"t":"美國","s":"美国","d":290},{"t":"從未","l":"7-9","s":"从未","d":291},{"t":"出版","l":"5","d":292},{"t":"，"},{"t":"其","l":"5","d":293},{"t":"作者","l":"3","d":294},{"t":"1936"},{"t":"年","l":"1","d":274},{"t":"逝世","l":"7-9","d":295},{"t":"，"},{"t":"在","l":"1","d":224},{"t":"美國","s":"美国","d":290},{"t":"以及","l":"4","d":296},{"t":"版權","s":"版权","d":297},{"t":"期限","l":"4","d":298},{"t":"是","l":"1","d":3},{"t":"作者","l":"3","d":294},{"t":"終身","l":"5","s":"终身","d":299},{"t":"加","l":"2","d":300},{"t":"80"},{"t":"年","l":"1","d":274},{"t":"以下","l":"2","d":301},{"t":"的","l":"1","d":34},{"t":"國家","l":"1","s":"国家","d":283},{"t":"以及","l":"4","d":296},{"t":"地区","l":"3","d":302},{"t":"，"},{"t":"屬於","l":"3","s":"属于","d":286},{"t":"公有","d":287},{"t":"領域","l":"7-9","s":"领域","d":288},{"t":"。"}],[{"t":"这","l":"1","d":279},{"t":"部","l":"3","d":280},{"t":"作品","l":"3","d":281},{"t":"也","l":"1","d":9},{"t":"可能","l":"2","d":303},{"t":"在","l":"1","d":224},{"t":"本國","s":"本国","d":304},{"t":"本地","l":"6","d":305},{"t":"版權","s":"版权","d":297},{"t":"期限","l":"4","d":298},{"t":"更","l":"2","d":306},{"t":"長","l":"2","s":"长","d":307},{"t":"，"},{"t":"但","l":"2","d":308},{"t":"對外","l":"6","s":"对外","d":309},{"t":"國外","l":"1","s":"国外","d":310},{"t":"地","l":"1","d":20},{"t":"作品","l":"3","d":281},{"t":"應用","l":"3","s":"应用","d":311},{"t":"較","l":"3","s":"较","d":312},{"t":"短期","l":"3","d":313},{"t":"限","l":"7-9","d":314},{"t":"規則","l":"4","s":"规则","d":315},{"t":"的","l":"1","d":34},{"t":"國家","l":"1","s":"国家","d":283},{"t":"以及","l":"4","d":296},{"t":"地区","l":"3","d":302},{"t":"，"},{"t":"屬於","l":"3","s":"属于","d":286},{"t":"公有","d":287},{"t":"領域","l":"7-9","s":"领域","d":288},{"t":"。"}],[{"t":"Public domainPublic domainfalsefalse"}]],"dict":[[{"trad":"奴才","simp":"奴才","pinyin":"nú cai","defs":"slave / fig. flunkey","hsk":null}],[{"trad":"總","simp":"总","pinyin":"zǒng","defs":"(bound form) general; overall / to sum up / in every case; always; invariably / anyway; after all; eventually; sooner or later / surely / (after a person's name) abbr. for 總經理|总经理[zong3 jing1 li3] or 總編|总编[zong3 bian1] etc","hsk":"3","a":1,"pos":"副、（动、形）"}],[{"trad":"不過","simp":"不过","pinyin":"bù guò","defs":"only / merely / no more than / but / however / anyway (to get back to a previous topic) / cannot be more (after adjectival)","hsk":"2","a":1,"pos":"连、（副）"}],[{"trad":"是","simp":"是","pinyin":"shì","defs":"to be (followed by substantives only) / correct; right; true / (respectful acknowledgement of a command) very well / (adverb for emphatic assertion)","hsk":"1","a":1,"pos":"动"},{"trad":"昰","simp":"是","pinyin":"shì","defs":"variant of 是[shi4]","hsk":"1","a":1,"pos":"动"}],[{"trad":"尋","simp":"寻","pinyin":"xún","defs":"to search / to look for / to seek","hsk":"7-9","a":1,"pos":"动"}],[{"trad":"人","simp":"人","pinyin":"rén","defs":"person; people / CL:個|个[ge4],位[wei4],名[ming2]","hsk":"1","a":1,"pos":"名"}],[{"trad":"訴苦","simp":"诉苦","pinyin":"sù kǔ","defs":"to grumble / to complain / grievance","hsk":"7-9","a":1,"pos":"动"}],[{"trad":"只要","simp":"只要","pinyin":"zhǐ yào","defs":"so long as; provided; if","hsk":"2","a":1,"pos":"连"}],[{"trad":"這樣","simp":"这样","pinyin":"zhè yàng","defs":"this way; like this; so / (before a noun) this kind of; such","hsk":"2","a":1,"pos":"代"}],[{"trad":"也","simp":"也","pinyin":"Yě","defs":"surname Ye","hsk":"1","a":1,"pos":"副"},{"trad":"也","simp":"也","pinyin":"yě","defs":"also; too; as well; (not ...) either / (used after a verbal or nominal expression X to indicate that X is an extreme or unexpected case) even (X) / (literary) particle having functions similar to 啊[a5]","hsk":"1","a":1,"pos":"副"}],[{"trad":"只能","simp":"只能","pinyin":"zhǐ néng","defs":"can only / obliged to do sth / to have no other choice","hsk":"2","a":1}],[{"trad":"有","simp":"有","pinyin":"yǒu","defs":"to have; there is / (bound form) having; with; -ful; -ed; -al (as in 有意[you3 yi4] intentional)","hsk":"1","a":1,"pos":"动"}],[{"trad":"一","simp":"一","pinyin":"yī","defs":"one / single / a (article) / as soon as / entire; whole; all; throughout / \"one\" radical in Chinese characters (Kangxi radical 1) / also pr. [yao1] for greater clarity when spelling out numbers digit by digit","hsk":"1","a":1,"pos":"数"}],[{"trad":"日","simp":"日","pinyin":"rì","defs":"(bound form) sun / day / day of the month / (bound form) Japan (abbr. for 日本[Ri4 ben3]) / (vulgar) to fuck; to have sex with","hsk":"1","a":1,"pos":"量、（名）"}],[{"trad":"他","simp":"他","pinyin":"tā","defs":"(third-person singular) (since the early 20th century, usu. male) he; him; his / (bound form) other; another; some other (as in 他日[ta1 ri4] and 他人[ta1 ren2])","hsk":"1","a":1,"pos":"代"}],[{"trad":"遇到","simp":"遇到","pinyin":"yù dào","defs":"to meet; to run into; to come across","hsk":"4","a":1,"pos":"动"}],[{"trad":"一個","simp":"一个","pinyin":"yī ge","defs":"a; an; one / the whole (afternoon, summer vacation etc)","hsk":null}],[{"trad":"聰明","simp":"聪明","pinyin":"cōng ming","defs":"intelligent; clever; bright / acute (of sight and hearing)","hsk":"5","a":1,"pos":"形"}],[{"trad":"先生","simp":"先生","pinyin":"xiān sheng","defs":"teacher / gentleman; sir; mister (Mr.) / husband / (dialect) doctor / CL:位[wei4]","hsk":"1","a":1,"pos":"名"}],[{"trad":"悲哀","simp":"悲哀","pinyin":"bēi āi","defs":"grieved / sorrowful","hsk":"7-9","a":1,"pos":"形"}],[{"trad":"地","simp":"地","pinyin":"de","defs":"-ly / structural particle: used before a verb or adjective, linking it to preceding modifying adverbial adjunct","hsk":"1","a":1,"pos":"助、名"},{"trad":"地","simp":"地","pinyin":"dì","defs":"earth / ground / field / place / land / CL:片[pian4]","hsk":"1","a":1,"pos":"助、名"}],[{"trad":"說","simp":"说","pinyin":"shuì","defs":"to persuade","hsk":"1","a":1,"pos":"动"},{"trad":"說","simp":"说","pinyin":"shuō","defs":"to speak; to talk; to say / to explain; to comment / to scold; to tell off / (bound form) theory; doctrine","hsk":"1","a":1,"pos":"动"}],[{"trad":"眼淚","simp":"眼泪","pinyin":"yǎn lèi","defs":"tear; teardrop / CL:滴[di1]","hsk":"4","a":1,"pos":"名"}],[{"trad":"聯","simp":"联","pinyin":"lián","defs":"(bound form) to ally oneself with; to unite; to combine; to join / (bound form) (poetry) antithetical couplet","hsk":null}],[{"trad":"成","simp":"成","pinyin":"Chéng","defs":"surname Cheng / short name for Chengdu 成都[Cheng2 du1]","hsk":"2","a":1,"pos":"量"},{"trad":"成","simp":"成","pinyin":"chéng","defs":"to succeed / to finish / to complete / to accomplish / to become / to turn into / to be all right / OK! / one tenth","hsk":"2","a":1,"pos":"量"}],[{"trad":"一線","simp":"一线","pinyin":"yī xiàn","defs":"front line","hsk":"7-9","a":1,"pos":"名"}],[{"trad":"就","simp":"就","pinyin":"jiù","defs":"(after a suppositional clause) in that case; then / (after a clause of action) as soon as; immediately after / (same as 就是[jiu4 shi4]) merely; nothing else but; simply; just; precisely; exactly / only; as little as / as much as; as many as / to approach; to move towards / to undertake; to engage in / (often followed by 著|着[zhe5]) taking advantage of / (of food) to go with / with regard to; concerning / (bound form) to reach; to attain (as in 一蹴而就[yi1 cu4 er2 jiu4]) / (pattern: 就[jiu4] ... 也[ye3] ...) even if ... still ... / (pattern: 不[bu4] ... 就[jiu4] ...) if not ... then must be ...","hsk":"1","a":1,"pos":"副、（介）"}],[{"trad":"從","simp":"从","pinyin":"Cóng","defs":"surname Cong","hsk":"1","a":1,"pos":"介、（副）"},{"trad":"從","simp":"从","pinyin":"cóng","defs":"from; through; via / (bound form) to follow / (bound form) to obey / (bound form) to engage in (an activity) / (used before a negative) ever / (bound form) (Taiwan pr. [zong4]) retainer; attendant / (bound form) (Taiwan pr. [zong4]) assistant; auxiliary; subordinate / (bound form) (Taiwan pr. [zong4]) related by common paternal grandfather or earlier ancestor","hsk":"1","a":1,"pos":"介、（副）"}],[{"trad":"眼角","simp":"眼角","pinyin":"yǎn jiǎo","defs":"outer or inner corner of the eye; canthus","hsk":null}],[{"trad":"上","simp":"上","pinyin":"shǎng","defs":"used in 上聲|上声[shang3 sheng1]","hsk":"1","a":1,"pos":"名、动"},{"trad":"上","simp":"上","pinyin":"shàng","defs":"(bound form) up; upper; above; previous / first (of multiple parts) / to climb; to get onto; to go up / to attend (class or university) / (directional complement) up / (noun suffix) on; above","hsk":"1","a":1,"pos":"名、动"}],[{"trad":"直流","simp":"直流","pinyin":"zhí liú","defs":"to flow steadily / direct current (DC)","hsk":null}],[{"trad":"下來","simp":"下来","pinyin":"xià lai","defs":"to come down / (completed action marker) / (after verb of motion, indicates motion down and towards us, also fig.) / (indicates continuation from the past towards us) / to be harvested (of crops) / to be over (of a period of time) / to go among the masses (said of leaders)","hsk":"3","a":1,"pos":"动"}],[{"trad":"你","simp":"你","pinyin":"nǐ","defs":"you (informal, as opposed to courteous 您[nin2])","hsk":"1","a":1,"pos":"代"},{"trad":"妳","simp":"你","pinyin":"nǐ","defs":"you (Note: In Taiwan, 妳 is used to address females, but in mainland China, it is not commonly used. Instead, 你 is used to address both males and females.)","hsk":"1","a":1,"pos":"代"}],[{"trad":"知道","simp":"知道","pinyin":"zhī dào","defs":"to know; to become aware of / also pr. [zhi1dao5]","hsk":"1","a":1,"pos":"动"}],[{"trad":"的","simp":"的","pinyin":"de","defs":"of; ~'s (possessive particle) / (used after an attribute when it modifies a noun) / (used at the end of a declarative sentence for emphasis) / (used after a noun, verb or adjective to form a nominal expression, as in 皮革的[pi2 ge2 de5] \"one made of leather\" or 跑堂兒的|跑堂儿的[pao3 tang2 r5 de5] \"a waiter (literally, one who runs back and forth in a restaurant)\" or 新的[xin1 de5] \"new one\") / also pr. [di4] or [di5] in poetry and songs","hsk":"1","a":1,"pos":"助"},{"trad":"的","simp":"的","pinyin":"dī","defs":"a taxi; a cab (abbr. for 的士[di1 shi4])","hsk":"1","a":1,"pos":"助"},{"trad":"的","simp":"的","pinyin":"dí","defs":"really and truly","hsk":"1","a":1,"pos":"助"},{"trad":"的","simp":"的","pinyin":"dì","defs":"(bound form) bull's-eye; target","hsk":"1","a":1,"pos":"助"}],[{"trad":"我","simp":"我","pinyin":"wǒ","defs":"I; me; my","hsk":"1","a":1,"pos":"代"}],[{"trad":"所","simp":"所","pinyin":"suǒ","defs":"actually / place / classifier for houses, small buildings, institutions etc / that which / particle introducing a relative clause or passive / CL:個|个[ge4]","hsk":"3","a":1,"pos":"量、名、助"}],[{"trad":"過","simp":"过","pinyin":"Guō","defs":"surname Guo","hsk":"1","a":1,"pos":"动"},{"trad":"過","simp":"过","pinyin":"guò","defs":"to cross / to go over / to pass (time) / to celebrate (a holiday) / to live / to get along / excessively / too-","hsk":"1","a":1,"pos":"动"},{"trad":"過","simp":"过","pinyin":"guo","defs":"(experienced action marker)","hsk":"1","a":1,"pos":"动"}],[{"trad":"簡直","simp":"简直","pinyin":"jiǎn zhí","defs":"simply; really","hsk":"3","a":1,"pos":"副"}],[{"trad":"不是","simp":"不是","pinyin":"bù shì","defs":"no / is not / not","hsk":null},{"trad":"不是","simp":"不是","pinyin":"bù shi","defs":"fault; blame","hsk":null}],[{"trad":"生活","simp":"生活","pinyin":"shēng huó","defs":"to live / life / livelihood","hsk":"2","a":1,"pos":"名、动"}],[{"trad":"喫","simp":"吃","pinyin":"chī","defs":"variant of 吃[chi1]","hsk":"1","a":1,"pos":"动"}],[{"trad":"天","simp":"天","pinyin":"tiān","defs":"day / sky / heaven","hsk":"1","a":1,"pos":"名、量"}],[{"trad":"未必","simp":"未必","pinyin":"wèi bì","defs":"not necessarily / maybe not","hsk":"4","a":1,"pos":"副"}],[{"trad":"餐","simp":"餐","pinyin":"cān","defs":"meal / to eat / classifier for meals","hsk":"6"}],[{"trad":"這","simp":"这","pinyin":"zhè","defs":"(pronoun) this; these / (bound form) this; the (followed by a noun) / (bound form) this; these (followed by a classifier) (in this sense, commonly pr. [zhei4], esp. in Beijing)","hsk":"1","a":1,"pos":"代"},{"trad":"這","simp":"这","pinyin":"zhèi","defs":"(coll.) this","hsk":"1","a":1,"pos":"代"}],[{"trad":"又","simp":"又","pinyin":"yòu","defs":"(once) again / also / both... and... / and yet / (used for emphasis) anyway","hsk":"2","a":1,"pos":"副"}],[{"trad":"高粱","simp":"高粱","pinyin":"gāo liáng","defs":"sorghum / common sorghum (Sorghum vulgare)","hsk":null}],[{"trad":"皮","simp":"皮","pinyin":"Pí","defs":"surname Pi","hsk":"3","a":1,"pos":"名、形"},{"trad":"皮","simp":"皮","pinyin":"pí","defs":"skin; peel; rind; outer layer / leather; hide; fur / cover; wrapping; outer covering / (of food) no longer crisp; soggy / (coll.) naughty; mischievous / pico- (10⁻¹²)","hsk":"3","a":1,"pos":"名、形"}],[{"trad":"連","simp":"连","pinyin":"Lián","defs":"surname Lian","hsk":"3","a":1,"pos":"介、（动、副）"},{"trad":"連","simp":"连","pinyin":"lián","defs":"to link / to join / to connect / continuously / in succession / including / (used with 也[ye3], 都[dou1] etc) even / company (military)","hsk":"3","a":1,"pos":"介、（动、副）"}],[{"trad":"豬狗","simp":"猪狗","pinyin":"zhū gǒu","defs":"pig-dog (intended as insult) / Schweinhund","hsk":null}],[{"trad":"都","simp":"都","pinyin":"Dū","defs":"surname Du","hsk":"1","a":1,"pos":"副"},{"trad":"都","simp":"都","pinyin":"dōu","defs":"all; both; entirely / (used for emphasis) even / already / (not) at all","hsk":"1","a":1,"pos":"副"},{"trad":"都","simp":"都","pinyin":"dū","defs":"capital city / metropolis","hsk":"1","a":1,"pos":"副"}],[{"trad":"不要","simp":"不要","pinyin":"bù yào","defs":"don't!; must not","hsk":"2","a":1,"pos":"副"}],[{"trad":"尙","simp":"尙","pinyin":"shàng","defs":"variant of 尚, still / yet / to value / to esteem","hsk":null}],[{"trad":"且","simp":"且","pinyin":"qiě","defs":"and / moreover / yet / for the time being / to be about to / both (... and...)","hsk":"7-9","a":1,"pos":"连"}],[{"trad":"只有","simp":"只有","pinyin":"zhǐ yǒu","defs":"only have ...; there is only ... / (used in combination with 才[cai2]) it is only if ... (that one can ...) (as in 只有通過治療才能痊愈|只有通过治疗才能痊愈[zhi3 you3 tong1 guo4 zhi4 liao2 cai2 neng2 quan2 yu4] \"the only way to cure it is with therapy\") / it is only (someone) who ... (as in 只有男性才有此需要[zhi3 you3 nan2 xing4 cai2 you3 ci3 xu1 yao4] \"only men would have such a requirement\") / (used to express lack of alternatives) can only; have no choice but to (as in 只有屈服[zhi3 you3 qu1 fu2] \"the only thing you can do is give in\")","hsk":"3","a":1,"pos":"连"}],[{"trad":"小","simp":"小","pinyin":"xiǎo","defs":"small / tiny / few / young","hsk":"1","a":1,"pos":"形、前缀"}],[{"trad":"碗","simp":"碗","pinyin":"wǎn","defs":"bowl / cup / CL:隻|只[zhi1],個|个[ge4]","hsk":"2","a":1,"pos":"名"},{"trad":"㼝","simp":"碗","pinyin":"wǎn","defs":"variant of 碗[wan3]","hsk":"2","a":1,"pos":"名"},{"trad":"椀","simp":"碗","pinyin":"wǎn","defs":"variant of 碗[wan3]","hsk":"2","a":1,"pos":"名"},{"trad":"盌","simp":"碗","pinyin":"wǎn","defs":"variant of 碗[wan3]","hsk":"2","a":1,"pos":"名"}],[{"trad":"實","simp":"实","pinyin":"shí","defs":"real / true / honest / really / solid / fruit / seed / definitely","hsk":null}],[{"trad":"令人","simp":"令人","pinyin":"lìng rén","defs":"to cause one (to do sth) / to make one (angry, delighted etc)","hsk":null}],[{"trad":"同情","simp":"同情","pinyin":"tóng qíng","defs":"to sympathize with / sympathy","hsk":"4","a":1,"pos":"动"}],[{"trad":"慘然","simp":"惨然","pinyin":"cǎn rán","defs":"grieved / distressed","hsk":null}],[{"trad":"可不是","simp":"可不是","pinyin":"kě bu shì","defs":"(coll.) exactly!; indeed; that's for sure","hsk":"7-9","a":1,"pos":"副"}],[{"trad":"麽","simp":"么","pinyin":"me","defs":"variant of 麼|么[me5]","hsk":null},{"trad":"麼","simp":"麽","pinyin":"mó","defs":"tiny / insignificant","hsk":null}],[{"trad":"高興","simp":"高兴","pinyin":"gāo xìng","defs":"happy / glad / willing (to do sth) / in a cheerful mood","hsk":"1","a":1,"pos":"形"}],[{"trad":"了","simp":"了","pinyin":"le","defs":"(completed action marker) / (modal particle indicating change of state, situation now) / (modal particle intensifying preceding clause)","hsk":"1","a":1,"pos":"助"},{"trad":"了","simp":"了","pinyin":"liǎo","defs":"to finish / (used with 得[de2] or 不[bu4] after a verb to express (im)possibility, as in 忘不了[wang4 bu5 liao3] \"cannot forget\") / (literary) (usually followed by a negative such as 無|无[wu2] or 不[bu4]) completely (not); entirely (not); (not) in the least / to understand clearly (variant of 瞭|了[liao3])","hsk":"1","a":1,"pos":"助"},{"trad":"瞭","simp":"了","pinyin":"liǎo","defs":"(of eyes) bright / clear-sighted / to understand clearly","hsk":"1","a":1,"pos":"助"},{"trad":"瞭","simp":"了","pinyin":"liào","defs":"unofficial variant of 瞭[liao4]","hsk":"1","a":1,"pos":"助"}],[{"trad":"可是","simp":"可是","pinyin":"kě shì","defs":"but; however / (used for emphasis) indeed","hsk":"2","a":1,"pos":"连"}],[{"trad":"做工","simp":"做工","pinyin":"zuò gōng","defs":"to work with one's hands / manual work / workmanship","hsk":null}],[{"trad":"晝夜","simp":"昼夜","pinyin":"zhòu yè","defs":"day and night / period of 24 hours / continuously, without stop","hsk":"7-9","a":1,"pos":"名"}],[{"trad":"無","simp":"无","pinyin":"mó","defs":"used in 南無|南无[na1 mo2]","hsk":"4","a":1,"pos":"动"},{"trad":"無","simp":"无","pinyin":"wú","defs":"not to have / no / none / not / to lack / un- / -less","hsk":"4","a":1,"pos":"动"}],[{"trad":"休息","simp":"休息","pinyin":"xiū xi","defs":"rest / to rest","hsk":"1","a":1,"pos":"动"}],[{"trad":"淸","simp":"淸","pinyin":"qīng","defs":"variant of 清[qing1]","hsk":null}],[{"trad":"早","simp":"早","pinyin":"zǎo","defs":"early / morning / Good morning! / long ago / prematurely","hsk":"1","a":1,"pos":"形"}],[{"trad":"擔","simp":"担","pinyin":"dān","defs":"to undertake / to carry / to shoulder / to take responsibility","hsk":"7-9","a":1,"pos":"动"},{"trad":"擔","simp":"担","pinyin":"dàn","defs":"picul (100 catties, 50 kg) / two buckets full / carrying pole and its load / classifier for loads carried on a shoulder pole","hsk":"7-9","a":1,"pos":"动"}],[{"trad":"水","simp":"水","pinyin":"Shuǐ","defs":"surname Shui / Shui ethnic group","hsk":"1","a":1,"pos":"名"},{"trad":"水","simp":"水","pinyin":"shuǐ","defs":"water / (after a name) ... River / to swim (used mostly in 會水|会水[hui4 shui3] and 水性[shui3 xing4]) / (coll.) lacking in substance; shoddy / (bound form) additional cost; extra income / classifier for washings of a garment","hsk":"1","a":1,"pos":"名"}],[{"trad":"晚","simp":"晚","pinyin":"wǎn","defs":"evening / night / late","hsk":"1","a":1,"pos":"形"}],[{"trad":"燒","simp":"烧","pinyin":"shāo","defs":"to burn; to set on fire / to heat (over a fire); to boil (water, tea etc) / to braise / to cook; to prepare food / to run a fever / fever / (coll.) to become full of oneself; to get carried away","hsk":"4","a":1,"pos":"动、名"}],[{"trad":"飯","simp":"饭","pinyin":"fàn","defs":"cooked rice / CL:碗[wan3] / meal / CL:頓|顿[dun4] / (loanword) fan / devotee","hsk":"1","a":1,"pos":"名"}],[{"trad":"上午","simp":"上午","pinyin":"shàng wǔ","defs":"morning","hsk":"1","a":1,"pos":"名"}],[{"trad":"跑","simp":"跑","pinyin":"páo","defs":"(of an animal) to paw (the ground)","hsk":"1","a":1,"pos":"动"},{"trad":"跑","simp":"跑","pinyin":"pǎo","defs":"to run / to run away / to escape / to run around (on errands etc) / (of a gas or liquid) to leak or evaporate / (verb complement) away / off","hsk":"1","a":1,"pos":"动"}],[{"trad":"街","simp":"街","pinyin":"jiē","defs":"street / CL:條|条[tiao2]","hsk":"2","a":1,"pos":"名"}],[{"trad":"夜","simp":"夜","pinyin":"yè","defs":"night","hsk":"2","a":1,"pos":"名、量"},{"trad":"亱","simp":"夜","pinyin":"yè","defs":"variant of 夜[ye4]","hsk":"2","a":1,"pos":"名、量"}],[{"trad":"磨","simp":"磨","pinyin":"mó","defs":"to rub / to grind / to polish / to sharpen / to wear down / to die out / to waste time / to pester / to insist","hsk":"6","a":1,"pos":"动"},{"trad":"磨","simp":"磨","pinyin":"mò","defs":"grindstone / to grind / to turn round","hsk":"6","a":1,"pos":"动"}],[{"trad":"麫","simp":"麫","pinyin":"miàn","defs":"variant of 麵|面[mian4]","hsk":null}],[{"trad":"晴","simp":"晴","pinyin":"qíng","defs":"clear / fine (weather)","hsk":"2","a":1,"pos":"形"}],[{"trad":"洗衣","simp":"洗衣","pinyin":"xǐ yī","defs":"laundry","hsk":null}],[{"trad":"裳","simp":"裳","pinyin":"cháng","defs":"lower garment / skirts / petticoats / garments","hsk":null},{"trad":"裳","simp":"裳","pinyin":"shang","defs":"used in 衣裳[yi1 shang5]","hsk":null}],[{"trad":"雨","simp":"雨","pinyin":"yǔ","defs":"rain / CL:陣|阵[zhen4],場|场[chang2]","hsk":"1","a":1,"pos":"名"},{"trad":"雨","simp":"雨","pinyin":"yù","defs":"(literary) to rain / (of rain, snow etc) to fall / to precipitate / to wet","hsk":"1","a":1,"pos":"名"}],[{"trad":"張","simp":"张","pinyin":"Zhāng","defs":"surname Zhang","hsk":"3","a":1,"pos":"动、量"},{"trad":"張","simp":"张","pinyin":"zhāng","defs":"to open up / to spread / sheet of paper / classifier for flat objects, sheet / classifier for votes","hsk":"3","a":1,"pos":"动、量"}],[{"trad":"傘","simp":"伞","pinyin":"sǎn","defs":"umbrella / parasol / CL:把[ba3]","hsk":"4","a":1,"pos":"名"}],[{"trad":"冬","simp":"冬","pinyin":"dōng","defs":"winter","hsk":null},{"trad":"鼕","simp":"冬","pinyin":"Dōng","defs":"surname Dong","hsk":null},{"trad":"鼕","simp":"冬","pinyin":"dōng","defs":"(onom.) beating a drum / rat-a-tat","hsk":null}],[{"trad":"汽","simp":"汽","pinyin":"qì","defs":"steam / vapor","hsk":null}],[{"trad":"鑪","simp":"炉","pinyin":"lú","defs":"variant of 爐|炉[lu2]","hsk":null},{"trad":"鑪","simp":"𬬻","pinyin":"lú","defs":"rutherfordium (chemistry)","hsk":null}],[{"trad":"夏","simp":"夏","pinyin":"Xià","defs":"the Xia or Hsia dynasty c. 2000 BC / Xia of the Sixteen Kingdoms (407–432) / surname Xia","hsk":null},{"trad":"夏","simp":"夏","pinyin":"xià","defs":"summer","hsk":null}],[{"trad":"打","simp":"打","pinyin":"dá","defs":"(loanword) dozen / Taiwan pr. [da3]","hsk":"1","a":1,"pos":"动、介"},{"trad":"打","simp":"打","pinyin":"dǎ","defs":"a semantically light, transitive verb that is combined with various grammatical objects to form compound verbs and verb-object phrases with a diverse range of meanings (e.g. 打傘|打伞[da3 san3] \"to hold an umbrella\", 打電話|打电话[da3 dian4 hua4] \"to make a phone call\", 打針|打针[da3 zhen1] \"to get an injection\", 打手套[da3 shou3 tao4] \"to knit gloves\", 打氣|打气[da3 qi4] \"to inflate\") / to hit; to strike / to fight / (coll.) from; since (as in 打那以後|打那以后[da3 na4 yi3 hou4] \"since then\")","hsk":"1","a":1,"pos":"动、介"}],[{"trad":"扇","simp":"扇","pinyin":"shān","defs":"to fan / to slap sb on the face","hsk":"5","a":1,"pos":"动、量"},{"trad":"扇","simp":"扇","pinyin":"shàn","defs":"fan / sliding, hinged or detachable flat part of sth / classifier for doors, windows etc","hsk":"5","a":1,"pos":"动、量"}],[{"trad":"半夜","simp":"半夜","pinyin":"bàn yè","defs":"midnight / in the middle of the night","hsk":"2","a":1,"pos":"数量、名"}],[{"trad":"要","simp":"要","pinyin":"yāo","defs":"(bound form) to demand; to coerce","hsk":"1","a":1,"pos":"动"},{"trad":"要","simp":"要","pinyin":"yào","defs":"to want; to need; to ask for / will; shall; about to / need to; should / if (same as 要是[yao4 shi5]) / (bound form) important","hsk":"1","a":1,"pos":"动"}],[{"trad":"煨","simp":"煨","pinyin":"wēi","defs":"to simmer / to roast in ashes","hsk":null}],[{"trad":"銀耳","simp":"银耳","pinyin":"yín ěr","defs":"white fungus (Tremella fuciformis) / silver tree-ear fungus","hsk":null}],[{"trad":"侍候","simp":"侍候","pinyin":"shì hòu","defs":"to serve / to wait upon","hsk":"7-9","a":1,"pos":"动"}],[{"trad":"主人","simp":"主人","pinyin":"zhǔ rén","defs":"master / host / owner / CL:個|个[ge4]","hsk":"2","a":1,"pos":"名"}],[{"trad":"耍錢","simp":"耍钱","pinyin":"shuǎ qián","defs":"(coll.) to gamble","hsk":null}],[{"trad":"頭","simp":"头","pinyin":"tóu","defs":"head / hair style / the top / end / beginning or end / a stub / remnant / chief / boss / side / aspect / first / leading / classifier for pigs or livestock / CL:個|个[ge4]","hsk":"2","a":1,"pos":"名、（量）、（形）、后缀"},{"trad":"頭","simp":"头","pinyin":"tou","defs":"suffix for nouns","hsk":"2","a":1,"pos":"名、（量）、（形）、后缀"}],[{"trad":"錢","simp":"钱","pinyin":"Qián","defs":"surname Qian","hsk":"1","a":1,"pos":"名"},{"trad":"錢","simp":"钱","pinyin":"qián","defs":"coin / money / CL:筆|笔[bi3] / unit of weight, one tenth of a tael 兩|两[liang3]","hsk":"1","a":1,"pos":"名"}],[{"trad":"從來沒","simp":"从来没","pinyin":"cóng lái méi","defs":"have never / has never","hsk":null}],[{"trad":"分","simp":"分","pinyin":"fēn","defs":"to divide; to separate / to distribute; to allocate / to distinguish (good and bad) / (bound form) branch of (an organization); sub- (as in 分局[fen1 ju2]) / fraction / one tenth (of certain units) / unit of length equivalent to 0.33 cm / minute (unit of time) / minute (angular measurement unit) / a point (in sports or games) / 0.01 yuan (unit of money)","hsk":"1","a":1,"pos":"量、（动、名）"},{"trad":"分","simp":"分","pinyin":"fèn","defs":"part / share / ingredient / component","hsk":"1","a":1,"pos":"量、（动、名）"}],[{"trad":"有時","simp":"有时","pinyin":"yǒu shí","defs":"sometimes / now and then","hsk":"1","a":1,"pos":"副"}],[{"trad":"還","simp":"还","pinyin":"Huán","defs":"surname Huan","hsk":"1","a":1,"pos":"副、动"},{"trad":"還","simp":"还","pinyin":"hái","defs":"still / still in progress / still more / yet / even more / in addition / fairly / passably (good) / as early as / even / also / else","hsk":"1","a":1,"pos":"副、动"},{"trad":"還","simp":"还","pinyin":"huán","defs":"to pay back / to return","hsk":"1","a":1,"pos":"副、动"}],[{"trad":"挨","simp":"挨","pinyin":"āi","defs":"in order; in sequence / close to; adjacent to","hsk":"6","a":1,"pos":"动、介"},{"trad":"挨","simp":"挨","pinyin":"ái","defs":"to suffer; to endure / to pull through (hard times) / to delay; to stall; to play for time; to dawdle","hsk":"6","a":1,"pos":"动、介"}],[{"trad":"皮鞭","simp":"皮鞭","pinyin":"pí biān","defs":"lash","hsk":null}],[{"trad":"唉唉","simp":"唉唉","pinyin":"āi āi","defs":"(onom.) sighing voice / crying sound","hsk":null}],[{"trad":"歎","simp":"叹","pinyin":"tàn","defs":"variant of 嘆|叹[tan4]","hsk":null}],[{"trad":"息","simp":"息","pinyin":"xī","defs":"breath / news / interest (on an investment or loan) / to cease / to stop / to rest / Taiwan pr. [xi2]","hsk":null}],[{"trad":"着","simp":"着","pinyin":"zhāo","defs":"variant of 著|着[zhao1]","hsk":"1","a":1,"pos":"助、动"},{"trad":"着","simp":"着","pinyin":"zháo","defs":"variant of 著|着[zhao2]","hsk":"1","a":1,"pos":"助、动"},{"trad":"着","simp":"着","pinyin":"zhe","defs":"variant of 著|着[zhe5]","hsk":"1","a":1,"pos":"助、动"},{"trad":"着","simp":"着","pinyin":"zhuó","defs":"variant of 著|着[zhuo2]","hsk":"1","a":1,"pos":"助、动"},{"trad":"著","simp":"着","pinyin":"zhāo","defs":"a move in chess (Taiwan pr. [zhuo2]) / trick; tactic / (dialect) okay; all right / (dialect) to put in; to add","hsk":"1","a":1,"pos":"助、动"},{"trad":"著","simp":"着","pinyin":"zháo","defs":"to touch / to come in contact with / to feel / to be affected by / to catch fire / to burn / (coll.) to fall asleep / (after a verb) hitting the mark / succeeding in","hsk":"1","a":1,"pos":"助、动"},{"trad":"著","simp":"着","pinyin":"zhe","defs":"aspect particle indicating action in progress or ongoing state","hsk":"1","a":1,"pos":"助、动"},{"trad":"著","simp":"着","pinyin":"zhuó","defs":"to wear (clothes) / to contact / to use / to apply","hsk":"1","a":1,"pos":"助、动"}],[{"trad":"眼圈","simp":"眼圈","pinyin":"yǎn quān","defs":"rim of the eye / eye socket","hsk":null}],[{"trad":"有些","simp":"有些","pinyin":"yǒu xiē","defs":"some / somewhat; rather; a bit","hsk":null,"a":1,"pos":"代、（副）"}],[{"trad":"發紅","simp":"发红","pinyin":"fā hóng","defs":"to turn red / to blush / to flush","hsk":null}],[{"trad":"似乎","simp":"似乎","pinyin":"sì hū","defs":"it seems; seemingly; as if","hsk":"4","a":1,"pos":"副"}],[{"trad":"下","simp":"下","pinyin":"xià","defs":"down / downwards / below / lower / later / next (week etc) / second (of two parts) / to decline / to go down / to arrive at (a decision, conclusion etc) / measure word to show the frequency of an action","hsk":"1","a":1,"pos":"名、动、量"}],[{"trad":"淚","simp":"泪","pinyin":"lèi","defs":"(bound form) tears; teardrops","hsk":"4","a":1,"pos":"名"}],[{"trad":"敷衍","simp":"敷衍","pinyin":"fū yǎn","defs":"to elaborate (on a theme) / to expound (the classics) / perfunctory / to skimp / to botch / to do sth half-heartedly or just for show / barely enough to get by","hsk":null,"a":1,"pos":"动"}],[{"trad":"不下","simp":"不下","pinyin":"bù xià","defs":"to be not less than (a certain quantity, amount etc)","hsk":null,"a":1,"pos":"动"}],[{"trad":"去","simp":"去","pinyin":"qù","defs":"to go / to go to (a place) / (of a time etc) last / just passed / to send / to remove / to get rid of / to reduce / to be apart from in space or time / to die (euphemism) / to play (a part) / (when used either before or after a verb) to go in order to do sth / (after a verb of motion indicates movement away from the speaker) / (used after certain verbs to indicate detachment or separation)","hsk":"1","a":1,"pos":"动"}],[{"trad":"總得","simp":"总得","pinyin":"zǒng děi","defs":"must / have to / be bound to","hsk":null}],[{"trad":"另外","simp":"另外","pinyin":"lìng wài","defs":"additional / in addition / besides / separate / other / moreover / furthermore","hsk":"3","a":1,"pos":"代、副、连"}],[{"trad":"想法","simp":"想法","pinyin":"xiǎng fǎ","defs":"way of thinking; opinion; notion / to think of a way (to do sth)","hsk":"2","a":1,"pos":"名"}],[{"trad":"子","simp":"子","pinyin":"zǐ","defs":"son / child / seed / egg / small thing / 1st earthly branch: 11 p.m.–1 a.m., midnight, 11th solar month (7th December to 5th January), year of the rat / viscount, fourth of five orders of nobility 五等爵位[wu3 deng3 jue2 wei4] / ancient Chinese compass point: 0° (north) / subsidiary; subordinate; (prefix) sub-","hsk":null,"a":1,"pos":"后缀"},{"trad":"子","simp":"子","pinyin":"zi","defs":"noun suffix, as in 椅子[yi3 zi5] \"chair\"","hsk":null,"a":1,"pos":"后缀"}],[{"trad":"什","simp":"什","pinyin":"shén","defs":"what","hsk":null},{"trad":"什","simp":"什","pinyin":"shí","defs":"ten (used in fractions, writing checks etc) / assorted / miscellaneous","hsk":null}],[{"trad":"法子","simp":"法子","pinyin":"fǎ zi","defs":"way / method / Taiwan pr. [fa2 zi5]","hsk":null}],[{"trad":"呢","simp":"呢","pinyin":"ne","defs":"(sentence-final particle) used in questions to link back to prior discourse or context (\"what about...?\", \"and...?\") / (sentence-final particle) indicating that a state or situation still holds / (discourse particle) used to mark a slight pause or emphasis in speech","hsk":"1","a":1,"pos":"助"},{"trad":"呢","simp":"呢","pinyin":"ní","defs":"dense wool fabric (used for coats and jackets)","hsk":"1","a":1,"pos":"助"}],[{"trad":"想","simp":"想","pinyin":"xiǎng","defs":"to think (about) / to think of; to devise / to think (that); to believe (that) / to desire; to want (to) / to miss (feel wistful about the absence of)","hsk":"1","a":1,"pos":"动"}],[{"trad":"會","simp":"会","pinyin":"huì","defs":"can; to have the skill; to know how to / to be likely to; to be sure to / to meet; to get together / meeting; gathering / (suffix) union; group; association / (bound form) a moment (Taiwan pr. [hui3])","hsk":"1","a":1,"pos":"动、名"},{"trad":"會","simp":"会","pinyin":"kuài","defs":"(bound form) to reckon accounts","hsk":"1","a":1,"pos":"动、名"}],[{"trad":"好起來","simp":"好起来","pinyin":"hǎo qǐ lai","defs":"to get better / to improve / to get well","hsk":null}],[{"trad":"但願如此","simp":"但愿如此","pinyin":"dàn yuàn rú cǐ","defs":"if only it were so / I hope so (idiom)","hsk":null}],[{"trad":"對","simp":"对","pinyin":"duì","defs":"right; correct / towards; at; for / concerning; regarding / to treat (sb a certain way) / to face / (bound form) opposite; facing; matching / to match together; to adjust / to fit; to suit / to answer; to reply / to add; to pour in (a fluid) / to check; to compare / classifier: couple; pair","hsk":"1","a":1,"pos":"形、介、（动、量）"}],[{"trad":"訴","simp":"诉","pinyin":"sù","defs":"to complain / to sue / to tell","hsk":null}],[{"trad":"寃","simp":"冤","pinyin":"yuān","defs":"old variant of 冤[yuan1]","hsk":"7-9","a":1,"pos":"名、形"}],[{"trad":"苦","simp":"苦","pinyin":"kǔ","defs":"bitter / hardship / pain / to suffer / to bring suffering to / painstakingly","hsk":"4","a":1,"pos":"形"}],[{"trad":"得","simp":"得","pinyin":"dé","defs":"to obtain / to get / to gain / to catch (a disease) / proper / suitable / proud / contented / to allow / to permit / ready / finished","hsk":"2","a":1,"pos":"助、动"},{"trad":"得","simp":"得","pinyin":"dè","defs":"used in 得瑟[de4 se5]","hsk":"2","a":1,"pos":"助、动"},{"trad":"得","simp":"得","pinyin":"de","defs":"structural particle: used after a verb (or adjective as main verb), linking it to following phrase indicating effect, degree, possibility etc","hsk":"2","a":1,"pos":"助、动"},{"trad":"得","simp":"得","pinyin":"děi","defs":"to have to / must / ought to / to need to","hsk":"2","a":1,"pos":"助、动"}],[{"trad":"和","simp":"和","pinyin":"Hé","defs":"surname He","hsk":"1","a":1,"pos":"介、连、形"},{"trad":"和","simp":"和","pinyin":"hé","defs":"(joining two nouns) and; together with; with (Taiwan pr. [han4]) / (math.) sum / to make peace / (sports) to draw; to tie / (bound form) harmonious / (bound form) Japan; Japanese","hsk":"1","a":1,"pos":"介、连、形"},{"trad":"和","simp":"和","pinyin":"hè","defs":"to compose a poem in reply (to sb's poem) using the same rhyme sequence / to join in the singing / to chime in with others","hsk":"1","a":1,"pos":"介、连、形"},{"trad":"和","simp":"和","pinyin":"hú","defs":"to complete a set in mahjong or playing cards","hsk":"1","a":1,"pos":"介、连、形"},{"trad":"和","simp":"和","pinyin":"huó","defs":"to combine a powdery substance (flour, plaster etc) with water / Taiwan pr. [huo4]","hsk":"1","a":1,"pos":"介、连、形"},{"trad":"和","simp":"和","pinyin":"huò","defs":"to mix (ingredients) together / to blend / classifier for rinses of clothes / classifier for boilings of medicinal herbs","hsk":"1","a":1,"pos":"介、连、形"},{"trad":"咊","simp":"和","pinyin":"hé","defs":"old variant of 和[he2]","hsk":"1","a":1,"pos":"介、连、形"},{"trad":"龢","simp":"和","pinyin":"hé","defs":"(literary) harmonious (variant of 和[he2])","hsk":"1","a":1,"pos":"介、连、形"}],[{"trad":"慰","simp":"慰","pinyin":"wèi","defs":"to comfort / to console / to reassure","hsk":null}],[{"trad":"安","simp":"安","pinyin":"Ān","defs":"surname An","hsk":"4","a":1,"pos":"形、动"},{"trad":"安","simp":"安","pinyin":"ān","defs":"(bound form) calm; peaceful / to calm; to set at ease / safe; secure; in good health / content; satisfied (as in 安於|安于[an1 yu2]) / to place (sb) in a suitable position (job) / to install; to fix; to fit / to bring (a charge against sb) / to harbor (certain intentions) / ampere (abbr. for 安培[an1 pei2])","hsk":"4","a":1,"pos":"形、动"}],[{"trad":"已經","simp":"已经","pinyin":"yǐ jīng","defs":"already","hsk":"2","a":1,"pos":"副"}],[{"trad":"舒坦","simp":"舒坦","pinyin":"shū tan","defs":"comfortable / at ease","hsk":null}],[{"trad":"不少","simp":"不少","pinyin":"bù shǎo","defs":"many; quite a few; a good number of","hsk":"2"}],[{"trad":"可見","simp":"可见","pinyin":"kě jiàn","defs":"it can clearly be seen (that this is the case) / it is (thus) clear / clear / visible","hsk":"4","a":1,"pos":"连"}],[{"trad":"天理","simp":"天理","pinyin":"tiān lǐ","defs":"Heaven's law / the natural order of things","hsk":null}],[{"trad":"沒有","simp":"没有","pinyin":"méi yǒu","defs":"haven't / hasn't / doesn't exist / to not have / to not be","hsk":"1","a":1,"pos":"动、副"}],[{"trad":"滅絕","simp":"灭绝","pinyin":"miè jué","defs":"to become extinct; to die out / to lose (sth abstract) completely / to exterminate","hsk":"7-9","a":1,"pos":"动"}],[{"trad":"但是","simp":"但是","pinyin":"dàn shì","defs":"but; however","hsk":"2","a":1,"pos":"连"}],[{"trad":"不","simp":"不","pinyin":"bù","defs":"no; not so / (bound form) not; un-","hsk":"1","a":1,"pos":"副"}],[{"trad":"幾","simp":"几","pinyin":"jī","defs":"(literary) almost","hsk":"1","a":1,"pos":"代、数"},{"trad":"幾","simp":"几","pinyin":"jǐ","defs":"how many; how much / several; a few","hsk":"1","a":1,"pos":"代、数"}],[{"trad":"不平","simp":"不平","pinyin":"bù píng","defs":"uneven / injustice / unfairness / wrong / grievance / indignant / dissatisfied","hsk":"7-9","a":1,"pos":"形"}],[{"trad":"起來","simp":"起来","pinyin":"qǐ lai","defs":"to stand up; to get up / also pr. [qi3lai2]","hsk":"1","a":1,"pos":"动"},{"trad":"起來","simp":"起来","pinyin":"qi lai","defs":"(after a verb) indicating the beginning and continuation of an action or a state / indicating an upward movement (e.g. after 站[zhan4]) / indicating completion / (after a perception verb, e.g. 看[kan4]) expressing preliminary judgment / also pr. [qi3lai5]","hsk":"1","a":1,"pos":"动"}],[{"trad":"仍然","simp":"仍然","pinyin":"réng rán","defs":"still; as before; yet","hsk":"3","a":1,"pos":"副"}],[{"trad":"流","simp":"流","pinyin":"liú","defs":"to flow / to disseminate / to circulate or spread / to move or drift / to degenerate / to banish or send into exile / stream of water or sth resembling one / class, rate or grade","hsk":"2","a":1,"pos":"动"}],[{"trad":"著眼","simp":"着眼","pinyin":"zhuó yǎn","defs":"to have one's eyes on (a goal) / having sth in mind / to concentrate","hsk":"7-9","a":1,"pos":"动"}],[{"trad":"住","simp":"住","pinyin":"zhù","defs":"to live; to reside; to stay / to stop; to cease / (result complement indicating firmness or a stable achieved state)","hsk":"1","a":1,"pos":"动"}],[{"trad":"比","simp":"比","pinyin":"Bǐ","defs":"Belgium / Belgian / abbr. for 比利時|比利时[Bi3 li4 shi2]","hsk":"1","a":1,"pos":"动、介"},{"trad":"比","simp":"比","pinyin":"bī","defs":"euphemistic variant of 屄[bi1]","hsk":"1","a":1,"pos":"动、介"},{"trad":"比","simp":"比","pinyin":"bǐ","defs":"to compare / (followed by a noun and adjective) more {adj.} than {noun} / ratio / to gesture / (Taiwan pr. [bi4] in some compounds derived from Classical Chinese)","hsk":"1","a":1,"pos":"动、介"}],[{"trad":"豬","simp":"猪","pinyin":"zhū","defs":"hog / pig / swine / CL:口[kou3],頭|头[tou2]","hsk":"3","a":1,"pos":"名"}],[{"trad":"還不如","simp":"还不如","pinyin":"hái bù rú","defs":"to be better off ... / might as well ...","hsk":null}],[{"trad":"並不","simp":"并不","pinyin":"bìng bù","defs":"not at all; by no means","hsk":null}],[{"trad":"將","simp":"将","pinyin":"jiāng","defs":"will / shall / to use / to take / to checkmate / just a short while ago / (introduces object of main verb, used in the same way as 把[ba3])","hsk":"5","a":1,"pos":"介、副"},{"trad":"將","simp":"将","pinyin":"jiàng","defs":"(bound form) a general / (literary) to command; to lead / (Chinese chess) general (on the black side, equivalent to a king in Western chess)","hsk":"5","a":1,"pos":"介、副"},{"trad":"將","simp":"将","pinyin":"qiāng","defs":"to desire / to invite / to request","hsk":"5","a":1,"pos":"介、副"}],[{"trad":"當","simp":"当","pinyin":"dāng","defs":"to be / to act as / manage / withstand / when / during / ought / should / match equally / equal / same / obstruct / just at (a time or place) / on the spot / right / just at","hsk":"2","a":1,"pos":"动、介"},{"trad":"當","simp":"当","pinyin":"dàng","defs":"at or in the very same... / suitable / adequate / fitting / proper / to replace / to regard as / to think / to pawn / (coll.) to fail (a student)","hsk":"2","a":1,"pos":"动、介"}],[{"trad":"叭","simp":"叭","pinyin":"bā","defs":"denote a sound or sharp noise (gunfire etc)","hsk":null}],[{"trad":"兒","simp":"儿","pinyin":"ér","defs":"child / son","hsk":null},{"trad":"兒","simp":"儿","pinyin":"r","defs":"non-syllabic diminutive suffix / retroflex final","hsk":null}],[{"trad":"狗","simp":"狗","pinyin":"gǒu","defs":"dog / CL:隻|只[zhi1],條|条[tiao2]","hsk":"2","a":1,"pos":"名"}],[{"trad":"要好","simp":"要好","pinyin":"yào hǎo","defs":"to be on good terms / to be close friends / striving for self-improvement","hsk":"6","a":1,"pos":"形"}],[{"trad":"到","simp":"到","pinyin":"dào","defs":"to reach; to arrive / to leave for; to go to / to (a place); until (a time); up to (a point) / (verb complement indicating arriving at a place or reaching a point) / considerate; thoughtful; thorough","hsk":"1","a":1,"pos":"动"}],[{"trad":"萬","simp":"万","pinyin":"Wàn","defs":"surname Wan","hsk":"2","a":1,"pos":"数"},{"trad":"萬","simp":"万","pinyin":"wàn","defs":"ten thousand / a great number","hsk":"2","a":1,"pos":"数"}],[{"trad":"倍","simp":"倍","pinyin":"bèi","defs":"(two, three etc) -fold / times (multiplier) / double / to increase or multiply","hsk":"4","a":1,"pos":"量"}],[{"trad":"混","simp":"混","pinyin":"hún","defs":"muddy; turbid (variant of 渾|浑[hun2]) / brainless; foolish (variant of 渾|浑[hun2]) / Taiwan pr. [hun4]","hsk":"6","a":1,"pos":"动、副"},{"trad":"混","simp":"混","pinyin":"hùn","defs":"to mix / to mingle / muddled / to drift along / to muddle along / to pass for / to get along with sb / thoughtless / reckless","hsk":"6","a":1,"pos":"动、副"}],[{"trad":"帳","simp":"帐","pinyin":"zhàng","defs":"(bound form) curtain; tent; canopy / variant of 賬|账[zhang4]","hsk":null}],[{"trad":"那","simp":"那","pinyin":"Nā","defs":"surname Na","hsk":"1","a":1,"pos":"代、（连）"},{"trad":"那","simp":"那","pinyin":"Nuó","defs":"surname Nuo","hsk":"1","a":1,"pos":"代、（连）"},{"trad":"那","simp":"那","pinyin":"nǎ","defs":"variant of 哪[na3]","hsk":"1","a":1,"pos":"代、（连）"},{"trad":"那","simp":"那","pinyin":"nà","defs":"(specifier) that; the; those (colloquial pr. [nei4]) / (pronoun) that (referring to persons, things or situations) / then (in that case)","hsk":"1","a":1,"pos":"代、（连）"},{"trad":"那","simp":"那","pinyin":"nuó","defs":"(archaic) many / beautiful / how / old variant of 挪[nuo2]","hsk":"1","a":1,"pos":"代、（连）"}],[{"trad":"人大","simp":"人大","pinyin":"Rén dà","defs":"Renmin University of China (abbr. for 中國人民大學|中国人民大学[Zhong1 guo2 Ren2 min2 Da4 xue2])","hsk":null},{"trad":"人大","simp":"人大","pinyin":"rén dà","defs":"people's congress, a legislative body within the PRC's system of government at any of various levels – national, provincial, municipal, county or township (abbr. for 人民代表大會|人民代表大会[ren2 min2 dai4 biao3 da4 hui4])","hsk":null}],[{"trad":"叫","simp":"叫","pinyin":"jiào","defs":"to shout / to call / to order / to ask / to be called / by (indicates agent in the passive mood)","hsk":"1","a":1,"pos":"动、（介）"},{"trad":"呌","simp":"叫","pinyin":"jiào","defs":"variant of 叫[jiao4]","hsk":"1","a":1,"pos":"动、（介）"}],[{"trad":"使","simp":"使","pinyin":"shǐ","defs":"to make / to cause / to enable / to use / to employ / to send / to instruct sb to do sth / envoy / messenger","hsk":"3","a":1,"pos":"动"}],[{"trad":"驚","simp":"惊","pinyin":"jīng","defs":"to startle / to be frightened / to be scared / alarm","hsk":"7-9"}],[{"trad":"儍","simp":"儍","pinyin":"shǎ","defs":"variant of 傻[sha3]","hsk":null}],[{"trad":"只是","simp":"只是","pinyin":"zhǐ shì","defs":"merely; only; just; nothing but / simply / but; however","hsk":"3","a":1,"pos":"副、连"}],[{"trad":"間","simp":"间","pinyin":"jiān","defs":"between / among / within a definite time or space / room / section of a room or lateral space between two pairs of pillars / classifier for rooms","hsk":"1","a":1,"pos":"量、（名）"},{"trad":"間","simp":"间","pinyin":"jiàn","defs":"gap / to separate / to thin out (seedlings) / to sow discontent","hsk":"1","a":1,"pos":"量、（名）"}],[{"trad":"破","simp":"破","pinyin":"pò","defs":"broken / damaged / worn out / lousy / rotten / to break, split or cleave / to get rid of / to destroy / to break with / to defeat / to capture (a city etc) / to expose the truth of","hsk":"3","a":1,"pos":"动、形"}],[{"trad":"小屋","simp":"小屋","pinyin":"xiǎo wū","defs":"cabin / lodge / cottage / chalet / hut / shed","hsk":null}],[{"trad":"溼","simp":"湿","pinyin":"shī","defs":"variant of 濕|湿[shi1]","hsk":"4","a":1,"pos":"形"}],[{"trad":"陰","simp":"阴","pinyin":"Yīn","defs":"surname Yin","hsk":"2","a":1,"pos":"形"},{"trad":"陰","simp":"阴","pinyin":"yīn","defs":"overcast (weather) / cloudy / shady / Yin (the negative principle of Yin and Yang) / negative (electric.) / feminine / moon / implicit / hidden / genitalia","hsk":"2","a":1,"pos":"形"}],[{"trad":"滿","simp":"满","pinyin":"Mǎn","defs":"Manchu ethnic group","hsk":"2","a":1,"pos":"形、动"},{"trad":"滿","simp":"满","pinyin":"mǎn","defs":"to fill / full / filled / packed / fully / completely / quite / to reach the limit / to satisfy / satisfied / contented","hsk":"2","a":1,"pos":"形、动"}],[{"trad":"臭蟲","simp":"臭虫","pinyin":"chòu chóng","defs":"bedbug (Cimex lectularius) / tick","hsk":null}],[{"trad":"睡","simp":"睡","pinyin":"shuì","defs":"to sleep / to lie down","hsk":"1","a":1,"pos":"动"}],[{"trad":"下去","simp":"下去","pinyin":"xià qù","defs":"to go down / to descend / to go on / to continue / (of a servant) to withdraw","hsk":"3","a":1,"pos":"动"}],[{"trad":"咬","simp":"咬","pinyin":"yǎo","defs":"to bite / to nip","hsk":"5","a":1,"pos":"动"},{"trad":"齩","simp":"咬","pinyin":"yǎo","defs":"variant of 咬[yao3]","hsk":"5","a":1,"pos":"动"}],[{"trad":"眞","simp":"眞","pinyin":"zhēn","defs":"variant of 真[zhen1]","hsk":null}],[{"trad":"可以","simp":"可以","pinyin":"kě yǐ","defs":"can / may / possible / able to / not bad / pretty good","hsk":"2","a":1,"pos":"动、形"}],[{"trad":"穢","simp":"秽","pinyin":"huì","defs":"(bound form) dirty; filthy","hsk":null}],[{"trad":"氣","simp":"气","pinyin":"qì","defs":"gas; air / smell / weather / to make angry; to annoy; to get angry / vital energy; qi","hsk":"2","a":1,"pos":"名、动"}],[{"trad":"衝","simp":"冲","pinyin":"chōng","defs":"thoroughfare / to go straight ahead / to rush / to clash","hsk":"4","a":1,"pos":"动、介"},{"trad":"衝","simp":"冲","pinyin":"chòng","defs":"powerful / vigorous / pungent / towards / in view of","hsk":"4","a":1,"pos":"动、介"}],[{"trad":"鼻子","simp":"鼻子","pinyin":"bí zi","defs":"nose / CL:個|个[ge4],隻|只[zhi1]","hsk":"5","a":1,"pos":"名"}],[{"trad":"四面","simp":"四面","pinyin":"sì miàn","defs":"all sides","hsk":null}],[{"trad":"窗","simp":"窗","pinyin":"chuāng","defs":"window / CL:扇[shan4]","hsk":null,"a":1,"pos":"名"},{"trad":"牎","simp":"窗","pinyin":"chuāng","defs":"old variant of 窗[chuang1]","hsk":null,"a":1,"pos":"名"},{"trad":"牕","simp":"窗","pinyin":"chuāng","defs":"variant of 窗[chuang1]","hsk":null,"a":1,"pos":"名"},{"trad":"窓","simp":"窗","pinyin":"chuāng","defs":"variant of 窗[chuang1]","hsk":null,"a":1,"pos":"名"},{"trad":"窻","simp":"窗","pinyin":"chuāng","defs":"variant of 窗[chuang1]","hsk":null,"a":1,"pos":"名"}],[{"trad":"不會","simp":"不会","pinyin":"bù huì","defs":"improbable / unlikely / will not (act, happen etc) / not able / not having learned to do sth / (coll.) (Tw) don't mention it / not at all","hsk":null}],[{"trad":"開","simp":"开","pinyin":"kāi","defs":"to open (transitive or intransitive) / (of ships, vehicles, troops etc) to start / to turn on; to put in operation; to operate; to run / to boil / to write out (a prescription, check, invoice etc) / (directional complement) away; off / carat (gold) / abbr. for Kelvin, 開爾文|开尔文[Kai1 er3 wen2] / abbr. for 開本|开本[kai1 ben3], book format","hsk":"1","a":1,"pos":"动"}],[{"trad":"怎麽","simp":"怎么","pinyin":"zěn me","defs":"variant of 怎麼|怎么[zen3 me5]","hsk":"1","a":1,"pos":"代"}],[{"trad":"行","simp":"行","pinyin":"háng","defs":"(bound form) row; line / (bound form) line of business; trade; profession / (bound form) commercial firm / (bound form) to rank (first, second etc) among one's siblings (by age) / (in data tables) row; (Tw) column / classifier for rows or lines","hsk":"1","a":1,"pos":"动、形、名、量"},{"trad":"行","simp":"行","pinyin":"héng","defs":"used in 道行[dao4 heng2]","hsk":"1","a":1,"pos":"动、形、名、量"},{"trad":"行","simp":"行","pinyin":"xíng","defs":"(bound form) to walk; to go; to travel / (literary) trip; journey; visit / (bound form) temporary; makeshift / (bound form) current; in circulation / (bound form) to do; to perform / capable; competent / all right; OK!; will do / behavior; conduct (Taiwan pr. [xing4]) / (literary) about to; soon","hsk":"1","a":1,"pos":"动、形、名、量"}],[{"trad":"那麽","simp":"那么","pinyin":"nà me","defs":"variant of 那麼|那么[na4 me5]","hsk":"2","a":1,"pos":"代、连"}],[{"trad":"帶","simp":"带","pinyin":"dài","defs":"band / belt / girdle / ribbon / tire / area / zone / region / CL:條|条[tiao2] / to wear / to carry / to take along / to bear (i.e. to have) / to lead / to bring / to look after / to raise","hsk":"2","a":1,"pos":"动、（名）"}],[{"trad":"我去","simp":"我去","pinyin":"wǒ qù","defs":"(slang) what the ...!; oh my god!; that's insane!","hsk":null}],[{"trad":"看","simp":"看","pinyin":"kān","defs":"to look after / to take care of / to watch / to guard","hsk":"1","a":1,"pos":"动"},{"trad":"看","simp":"看","pinyin":"kàn","defs":"to see; to look at / to read / to watch / to visit; to call on / to consider; to regard as / to look after / to treat (a patient or illness) / to depend on / to feel (that) / (after a verb) to give it a try / to watch out for","hsk":"1","a":1,"pos":"动"}],[{"trad":"跟","simp":"跟","pinyin":"gēn","defs":"heel / to follow closely / to go with / (of a woman) to marry sb / with / compared with / to / towards / and (joining two nouns)","hsk":"1","a":1,"pos":"介、连、（名、动）"}],[{"trad":"屋外","simp":"屋外","pinyin":"wū wài","defs":"outdoors; outside","hsk":null}],[{"trad":"動手","simp":"动手","pinyin":"dòng shǒu","defs":"to set about (a task) / to raise a hand to hit sb / to touch; to handle (typically used in cautioning sb *not* to touch sth)","hsk":"5","a":1,"pos":"动"}],[{"trad":"砸","simp":"砸","pinyin":"zá","defs":"to smash / to pound / to fail / to muck up / to bungle","hsk":"7-9","a":1,"pos":"动"}],[{"trad":"泥","simp":"泥","pinyin":"ní","defs":"mud / clay / paste / pulp","hsk":"6","a":1,"pos":"名"},{"trad":"泥","simp":"泥","pinyin":"nì","defs":"restrained","hsk":"6","a":1,"pos":"名"}],[{"trad":"牆","simp":"墙","pinyin":"qiáng","defs":"wall (CL:面[mian4],堵[du3]) / (slang) to block (a website) (usu. in the passive: 被牆|被墙[bei4 qiang2])","hsk":"2","a":1,"pos":"名"}],[{"trad":"幹","simp":"干","pinyin":"gàn","defs":"tree trunk / main part of sth / to manage / to work / to do / capable / cadre / to kill (slang) / to fuck (vulgar) / (coll.) pissed off / annoyed","hsk":"1","a":1,"pos":"动、形、（名）"}],[{"trad":"大驚","simp":"大惊","pinyin":"dà jīng","defs":"with great alarm","hsk":null}],[{"trad":"給","simp":"给","pinyin":"gěi","defs":"to / for / for the benefit of / to give / to allow / to do sth (for sb) / (grammatical equivalent of 被) / (grammatical equivalent of 把) / (sentence intensifier)","hsk":"1","a":1,"pos":"动、（介）"},{"trad":"給","simp":"给","pinyin":"jǐ","defs":"(bound form) to supply; to provide / (literary) sufficient; abundant","hsk":"1","a":1,"pos":"动、（介）"}],[{"trad":"打開","simp":"打开","pinyin":"dǎ kāi","defs":"to open / to show (a ticket) / to turn on / to switch on","hsk":"1","a":1,"pos":"动"}],[{"trad":"洞","simp":"洞","pinyin":"dòng","defs":"cave / hole / zero (unambiguous spoken form when spelling out numbers) / CL:個|个[ge4]","hsk":"5","a":1,"pos":"名"},{"trad":"洞","simp":"洞","pinyin":"tóng","defs":"used in 洪洞[Hong2 tong2] (the name of a place in Shanxi)","hsk":"5","a":1,"pos":"名"}],[{"trad":"來","simp":"来","pinyin":"lái","defs":"to come / (used as a substitute for a more specific verb) / hither (directional complement for motion toward the speaker, as in 回來|回来[hui2 lai5]) / ever since (as in 自古以來|自古以来[zi4 gu3 yi3 lai2]) / for the past (amount of time) / (prefix) the coming ...; the next ... (as in 來世|来世[lai2 shi4]) / (between two verbs) in order to / (after a round number) approximately / (used after 得[de2] to indicate possibility, as in 談得來|谈得来[tan2 de5 lai2], or after 不[bu4] to indicate impossibility, as in 吃不來|吃不来[chi1 bu5 lai2])","hsk":"1","a":1,"pos":"动"}],[{"trad":"這不","simp":"这不","pinyin":"zhè bu","defs":"(coll.) As a matter of fact, ... (used to introduce evidence for what one has just asserted)","hsk":null}],[{"trad":"罵","simp":"骂","pinyin":"mà","defs":"to scold / to abuse / to curse / CL:通[tong4],頓|顿[dun4]","hsk":"5","a":1,"pos":"动"}],[{"trad":"管他呢","simp":"管他呢","pinyin":"guǎn tā ne","defs":"don’t worry about (it, him etc) / doesn’t matter / whatever / anyway","hsk":null}],[{"trad":"呀","simp":"呀","pinyin":"yā","defs":"ah (used to express surprise) / (onom.) creaking","hsk":"4","a":1,"pos":"叹"},{"trad":"呀","simp":"呀","pinyin":"ya","defs":"(particle equivalent to 啊 after a vowel, expressing surprise or doubt)","hsk":"4","a":1,"pos":"叹"}],[{"trad":"強盜","simp":"强盗","pinyin":"qiáng dào","defs":"to rob (with force) / bandit / robber / CL:個|个[ge4]","hsk":"6","a":1,"pos":"名"}],[{"trad":"在","simp":"在","pinyin":"zài","defs":"to exist; to be alive / (of sb or sth) to be (located) at / (used before a verb to indicate an action in progress)","hsk":"1","a":1,"pos":"动、介、副"}],[{"trad":"毀","simp":"毁","pinyin":"huǐ","defs":"to destroy; to ruin / to defame; to slander","hsk":"6","a":1,"pos":"动"}],[{"trad":"咱們","simp":"咱们","pinyin":"zán men","defs":"we or us (including both the speaker and the person(s) spoken to) / (dialect) I or me / (dialect) (in a coaxing or familiar way) you / also pr. [za2 men5]","hsk":"2","a":1,"pos":"代"}],[{"trad":"屋子","simp":"屋子","pinyin":"wū zi","defs":"house / room / CL:間|间[jian1]","hsk":"3","a":1,"pos":"名"}],[{"trad":"快","simp":"快","pinyin":"kuài","defs":"rapid / quick / speed / rate / soon / almost / to make haste / clever / sharp (of knives or wits) / forthright / plainspoken / gratified / pleased / pleasant","hsk":"1","a":1,"pos":"形、副"}],[{"trad":"遲","simp":"迟","pinyin":"Chí","defs":"surname Chi","hsk":"5","a":1,"pos":"形"},{"trad":"遲","simp":"迟","pinyin":"chí","defs":"late / delayed / slow","hsk":"5","a":1,"pos":"形"}],[{"trad":"一點","simp":"一点","pinyin":"yī diǎn","defs":"a bit; a little bit / (used in negative expressions) (not) the least bit / (after an adjective, used to form the comparative) a bit more, -er / a point (in a discussion etc) / (calligraphy) dot stroke (、) / one o'clock (abbr. for 一點鍾|一点钟[yi1 dian3 zhong1])","hsk":null}],[{"trad":"可","simp":"可","pinyin":"kě","defs":"(prefix) can; may; able to; -able / to approve; to permit / to suit / (particle used for emphasis) certainly; very / but; however","hsk":"5","a":1,"pos":"连、（副）"},{"trad":"可","simp":"可","pinyin":"kè","defs":"used in 可汗[ke4 han2]","hsk":"5","a":1,"pos":"连、（副）"}],[{"trad":"出","simp":"出","pinyin":"chū","defs":"to go out; to come out / to arise; to occur / to produce; to yield / to go beyond; to exceed / (used after a verb to indicate an outward direction or a positive result) / classifier for dramas, plays, operas etc","hsk":"1","a":1,"pos":"动"},{"trad":"齣","simp":"出","pinyin":"chū","defs":"variant of 出[chu1] (classifier for plays or chapters of classical novels)","hsk":"1","a":1,"pos":"动"}],[{"trad":"窟窿","simp":"窟窿","pinyin":"kū long","defs":"hole / pocket / cavity / loophole / debt","hsk":"7-9","a":1,"pos":"名"}],[{"trad":"哭","simp":"哭","pinyin":"kū","defs":"to cry; to weep","hsk":"2","a":1,"pos":"动"}],[{"trad":"嚷","simp":"嚷","pinyin":"rǎng","defs":"to shout / to bellow / to make a big deal of sth / to make a fuss about sth","hsk":"7-9","a":1,"pos":"动"}],[{"trad":"在地","simp":"在地","pinyin":"zài dì","defs":"(Tw) local; native (from Taiwanese 在地, Tai-lo pr. [tsāi-tē])","hsk":null}],[{"trad":"團","simp":"团","pinyin":"tuán","defs":"round / lump / ball / to roll into a ball / to gather / regiment / group / society / classifier for a lump or a soft mass: wad (of paper), ball (of wool), cloud (of smoke)","hsk":"3","a":1,"pos":"动、名、量"}],[{"trad":"打滾","simp":"打滚","pinyin":"dǎ gǔn","defs":"to roll about","hsk":null}],[{"trad":"羣","simp":"群","pinyin":"qún","defs":"variant of 群[qun2]","hsk":"3","a":1,"pos":"量、名"}],[{"trad":"出來","simp":"出来","pinyin":"chū lái","defs":"to come out / to appear / to arise","hsk":"1","a":1,"pos":"动"},{"trad":"出來","simp":"出来","pinyin":"chu lai","defs":"(after a verb, indicates coming out, completion of an action, or ability to discern or detect)","hsk":"1","a":1,"pos":"动"}],[{"trad":"趕走","simp":"赶走","pinyin":"gǎn zǒu","defs":"to drive out / to turn back","hsk":null}],[{"trad":"聽到","simp":"听到","pinyin":"tīng dào","defs":"to hear","hsk":"1"}],[{"trad":"喊聲","simp":"喊声","pinyin":"hǎn shēng","defs":"to yell / hubbub","hsk":null}],[{"trad":"慢慢","simp":"慢慢","pinyin":"màn màn","defs":"slowly; gradually","hsk":"3"}],[{"trad":"最後","simp":"最后","pinyin":"zuì hòu","defs":"final; last; ultimate / finally; in the end","hsk":"1","a":1,"pos":"名"}],[{"trad":"首先","simp":"首先","pinyin":"shǒu xiān","defs":"first of all; in the first place","hsk":"3","a":1,"pos":"副、代"}],[{"trad":"叫喊","simp":"叫喊","pinyin":"jiào hǎn","defs":"exclamation / outcry / shout / yell","hsk":null}],[{"trad":"大家","simp":"大家","pinyin":"dà jiā","defs":"everyone / influential family / great expert","hsk":"2","a":1,"pos":"代"}],[{"trad":"一同","simp":"一同","pinyin":"yī tóng","defs":"together","hsk":"6","a":1,"pos":"副"}],[{"trad":"把","simp":"把","pinyin":"bǎ","defs":"to hold; to grasp / to hold a baby in position to help it urinate or defecate / handlebar / classifier: handful, bundle, bunch / classifier for things with handles / (used to put the object before the verb: 把[ba3] + {noun} + {verb})","hsk":"3","a":1,"pos":"量、介"},{"trad":"把","simp":"把","pinyin":"bà","defs":"handle","hsk":"3","a":1,"pos":"量、介"}],[{"trad":"恭敬","simp":"恭敬","pinyin":"gōng jìng","defs":"deferential / respectful","hsk":null,"a":1,"pos":"形"}],[{"trad":"而","simp":"而","pinyin":"ér","defs":"and / as well as / and so / but (not) / yet (not) / (indicates causal relation) / (indicates change of state) / (indicates contrast)","hsk":"4","a":1,"pos":"连"}],[{"trad":"得勝","simp":"得胜","pinyin":"dé shèng","defs":"to triumph over an opponent","hsk":null}],[{"trad":"不錯","simp":"不错","pinyin":"bù cuò","defs":"correct / right / not bad / pretty good","hsk":"2","a":1,"pos":"形"}],[{"trad":"誇獎","simp":"夸奖","pinyin":"kuā jiǎng","defs":"to praise / to applaud / to compliment","hsk":"7-9","a":1,"pos":"动"}],[{"trad":"許多","simp":"许多","pinyin":"xǔ duō","defs":"many / a lot of / much","hsk":"2","a":1,"pos":"数"}],[{"trad":"慰問","simp":"慰问","pinyin":"wèi wèn","defs":"to express sympathy, greetings, consolation etc","hsk":"5","a":1,"pos":"动"}],[{"trad":"在內","simp":"在内","pinyin":"zài nèi","defs":"(included) in it / among them","hsk":"5","a":1,"pos":"名"}],[{"trad":"回","simp":"回","pinyin":"Huí","defs":"Hui ethnic group (Chinese Muslims)","hsk":"1","a":1,"pos":"动、（量）"},{"trad":"回","simp":"回","pinyin":"huí","defs":"to go back; to return; to turn back; to turn around / to reply; to answer / classifier for literary divisions (acts of a play, sections or chapters of a classic book) / classifier for occurrences or times","hsk":"1","a":1,"pos":"动、（量）"},{"trad":"迴","simp":"回","pinyin":"huí","defs":"to curve / to return / to revolve","hsk":"1","a":1,"pos":"动、（量）"},{"trad":"逥","simp":"回","pinyin":"huí","defs":"variant of 迴|回[hui2]","hsk":"1","a":1,"pos":"动、（量）"}],[{"trad":"因","simp":"因","pinyin":"yīn","defs":"cause / reason / because","hsk":"6","a":1,"pos":"介、连"},{"trad":"囙","simp":"因","pinyin":"yīn","defs":"old variant of 因[yin1]","hsk":"6","a":1,"pos":"介、连"}],[{"trad":"爲","simp":"为","pinyin":"wéi","defs":"variant of 為|为[wei2]","hsk":"2","a":1,"pos":"介、动"},{"trad":"爲","simp":"为","pinyin":"wèi","defs":"variant of 為|为[wei4]","hsk":"2","a":1,"pos":"介、动"}],[{"trad":"功","simp":"功","pinyin":"gōng","defs":"meritorious deed or service / achievement / result / service / accomplishment / work (physics)","hsk":"7-9","a":1,"pos":"名"}],[{"trad":"先前","simp":"先前","pinyin":"xiān qián","defs":"before; previously","hsk":"5","a":1,"pos":"名"}],[{"trad":"實在","simp":"实在","pinyin":"shí zài","defs":"really / actually / indeed / true / real / honest / dependable / (philosophy) reality","hsk":"2","a":1,"pos":"形、副"}],[{"trad":"先見之明","simp":"先见之明","pinyin":"xiān jiàn zhī míng","defs":"foresight","hsk":null}],[{"trad":"大有希望","simp":"大有希望","pinyin":"dà yǒu xī wàng","defs":"to stand a good chance; to have great hopes; to be promising","hsk":null}],[{"trad":"似的","simp":"似的","pinyin":"shì de","defs":"seems as if / rather like / Taiwan pr. [si4 de5]","hsk":"4","a":1,"pos":"助"}],[{"trad":"嗎","simp":"吗","pinyin":"má","defs":"(coll.) what?","hsk":"1","a":1,"pos":"助"},{"trad":"嗎","simp":"吗","pinyin":"mǎ","defs":"used in 嗎啡|吗啡[ma3 fei1]","hsk":"1","a":1,"pos":"助"},{"trad":"嗎","simp":"吗","pinyin":"ma","defs":"(question particle for \"yes-no\" questions)","hsk":"1","a":1,"pos":"助"}],[{"trad":"代","simp":"代","pinyin":"dài","defs":"to be a substitute for; to act on behalf of; to replace; to substitute / generation; dynasty; age; period; (historical) era; (geological) eon","hsk":"3","a":1,"pos":"动、名"}],[{"trad":"回答","simp":"回答","pinyin":"huí dá","defs":"to reply; to answer / reply; answer","hsk":"1","a":1,"pos":"动"}],[{"trad":"九","simp":"九","pinyin":"jiǔ","defs":"nine / 9","hsk":"1","a":1,"pos":"数"}],[{"trad":"二","simp":"二","pinyin":"èr","defs":"two / 2 / (Beijing dialect) stupid","hsk":"1","a":1,"pos":"数"}],[{"trad":"五","simp":"五","pinyin":"wǔ","defs":"five / 5","hsk":"1","a":1,"pos":"数"}],[{"trad":"年","simp":"年","pinyin":"Nián","defs":"surname Nian","hsk":"1","a":1,"pos":"名、量"},{"trad":"年","simp":"年","pinyin":"nián","defs":"year / CL:個|个[ge4]","hsk":"1","a":1,"pos":"名、量"},{"trad":"秊","simp":"年","pinyin":"nián","defs":"grain / harvest (old) / variant of 年[nian2]","hsk":"1","a":1,"pos":"名、量"}],[{"trad":"十二月","simp":"十二月","pinyin":"Shí èr yuè","defs":"December / twelfth month (of the lunar year)","hsk":null}],[{"trad":"二十","simp":"二十","pinyin":"èr shí","defs":"twenty; 20","hsk":null}],[{"trad":"六","simp":"六","pinyin":"liù","defs":"six / 6","hsk":"1","a":1,"pos":"数"},{"trad":"六","simp":"六","pinyin":"lù","defs":"used in place names","hsk":"1","a":1,"pos":"数"}],[{"trad":"月","simp":"月","pinyin":"yuè","defs":"moon / month / monthly / CL:個|个[ge4],輪|轮[lun2]","hsk":"1","a":1,"pos":"名"}],[{"trad":"這","simp":"这","pinyin":"zhè","defs":"(pronoun) this; these / (bound form) this; the (followed by a noun) / (bound form) this; these (followed by a classifier) (in this sense, commonly pr. [zhei4], esp. in Beijing)","hsk":"1","a":1,"pos":"代"},{"trad":"這","simp":"这","pinyin":"zhèi","defs":"(coll.) this","hsk":"1","a":1,"pos":"代"}],[{"trad":"部","simp":"部","pinyin":"bù","defs":"ministry / department / section / part / division / troops / board / classifier for works of literature, films, machines etc","hsk":"3","a":1,"pos":"名、量"}],[{"trad":"作品","simp":"作品","pinyin":"zuò pǐn","defs":"work (of art) / opus / CL:部[bu4],篇[pian1]","hsk":"3","a":1,"pos":"名"}],[{"trad":"原作","simp":"原作","pinyin":"yuán zuò","defs":"original works / original text / original author","hsk":null}],[{"trad":"國家","simp":"国家","pinyin":"guó jiā","defs":"country; nation; state","hsk":"1","a":1,"pos":"名"}],[{"trad":"或","simp":"或","pinyin":"huò","defs":"maybe / perhaps / might / possibly / or","hsk":"2","a":1,"pos":"连、（副）"}],[{"trad":"地區","simp":"地区","pinyin":"dì qū","defs":"region; area (informal or geographical term) / prefecture (in China's administrative system)","hsk":"3","a":1,"pos":"名"}],[{"trad":"屬於","simp":"属于","pinyin":"shǔ yú","defs":"to belong to; to fall under (a category)","hsk":"3","a":1,"pos":"动"}],[{"trad":"公有","simp":"公有","pinyin":"gōng yǒu","defs":"publicly owned / communal / held in common","hsk":null}],[{"trad":"領域","simp":"领域","pinyin":"lǐng yù","defs":"domain; sphere; field; territory; area","hsk":"7-9","a":1,"pos":"名"}],[{"trad":"之前","simp":"之前","pinyin":"zhī qián","defs":"before / prior to / ago / previously / beforehand","hsk":"4","a":1,"pos":"名"}],[{"trad":"美國","simp":"美国","pinyin":"Měi guó","defs":"United States; USA; US","hsk":null}],[{"trad":"從未","simp":"从未","pinyin":"cóng wèi","defs":"never","hsk":"7-9","a":1,"pos":"副"}],[{"trad":"出版","simp":"出版","pinyin":"chū bǎn","defs":"to publish","hsk":"5","a":1,"pos":"动"}],[{"trad":"其","simp":"其","pinyin":"qí","defs":"his / her / its / their / that / such / it (refers to sth preceding it)","hsk":"5","a":1,"pos":"代"}],[{"trad":"作者","simp":"作者","pinyin":"zuò zhě","defs":"author; writer","hsk":"3","a":1,"pos":"名"}],[{"trad":"逝世","simp":"逝世","pinyin":"shì shì","defs":"to pass away / to die","hsk":"7-9","a":1,"pos":"动"}],[{"trad":"以及","simp":"以及","pinyin":"yǐ jí","defs":"and; as well as","hsk":"4","a":1,"pos":"连"}],[{"trad":"版權","simp":"版权","pinyin":"bǎn quán","defs":"copyright","hsk":null,"a":1,"pos":"名"}],[{"trad":"期限","simp":"期限","pinyin":"qī xiàn","defs":"time limit / deadline / allotted time","hsk":"4","a":1,"pos":"名"}],[{"trad":"終身","simp":"终身","pinyin":"zhōng shēn","defs":"lifelong / all one's life / marriage","hsk":"5","a":1,"pos":"名"}],[{"trad":"加","simp":"加","pinyin":"Jiā","defs":"Canada (abbr. for 加拿大[Jia1 na2 da4]) / surname Jia","hsk":"2","a":1,"pos":"动"},{"trad":"加","simp":"加","pinyin":"jiā","defs":"to add / (math.) plus / to increase; to augment / (used before a disyllabic verb, often after an adverb like 不[bu4], 大[da4], 稍[shao1] etc, to indicate that the action applies to sth previously mentioned, as in 稍加改良[shao1 jia1 gai3 liang2] \"make some minor improvements to (it)\")","hsk":"2","a":1,"pos":"动"}],[{"trad":"以下","simp":"以下","pinyin":"yǐ xià","defs":"that level or lower / that amount or less / the following","hsk":"2","a":1,"pos":"名"}],[{"trad":"地區","simp":"地区","pinyin":"dì qū","defs":"region; area (informal or geographical term) / prefecture (in China's administrative system)","hsk":"3","a":1,"pos":"名"}],[{"trad":"可能","simp":"可能","pinyin":"kě néng","defs":"might (happen) / possible / probable / possibility / probability / maybe / perhaps / CL:個|个[ge4]","hsk":"2","a":1,"pos":"形、名、动"}],[{"trad":"本國","simp":"本国","pinyin":"běn guó","defs":"one's own country","hsk":null}],[{"trad":"本地","simp":"本地","pinyin":"běn dì","defs":"local / this locality","hsk":"6","a":1,"pos":"名"}],[{"trad":"更","simp":"更","pinyin":"gēng","defs":"to change or replace / to experience / one of the five two-hour periods into which the night was formerly divided / watch (e.g. of a sentry or guard)","hsk":"2","a":1,"pos":"副"},{"trad":"更","simp":"更","pinyin":"gèng","defs":"more / even more / further / still / still more","hsk":"2","a":1,"pos":"副"}],[{"trad":"長","simp":"长","pinyin":"cháng","defs":"long / (bound form) length / (bound form) strong point; forte / (bound form) to be good at / (literary) surplus; spare (Taiwan pr. [zhang4])","hsk":"2","a":1,"pos":"形、动、后缀"},{"trad":"長","simp":"长","pinyin":"zhǎng","defs":"chief / head / elder / to grow / to develop / to increase / to enhance","hsk":"2","a":1,"pos":"形、动、后缀"}],[{"trad":"但","simp":"但","pinyin":"dàn","defs":"but; yet; however; still / merely; only; just","hsk":"2","a":1,"pos":"连、（副）"}],[{"trad":"對外","simp":"对外","pinyin":"duì wài","defs":"external / foreign / pertaining to external or foreign (affairs)","hsk":"6"}],[{"trad":"國外","simp":"国外","pinyin":"guó wài","defs":"abroad / external (affairs) / overseas / foreign","hsk":"1"}],[{"trad":"應用","simp":"应用","pinyin":"yìng yòng","defs":"to put to use; to apply / practical; applied (science, linguistics etc) / application; practical use / (computing) app","hsk":"3","a":1,"pos":"动、形"}],[{"trad":"較","simp":"较","pinyin":"jiào","defs":"(bound form) to compare / (literary) to dispute / compared to / (before an adjective) relatively; comparatively; rather / also pr. [jiao3]","hsk":"3","a":1,"pos":"介、副"}],[{"trad":"短期","simp":"短期","pinyin":"duǎn qī","defs":"short-term","hsk":"3","a":1,"pos":"名、形"}],[{"trad":"限","simp":"限","pinyin":"xiàn","defs":"to limit / to restrict / (bound form) limit / bound","hsk":"7-9","a":1,"pos":"动"}],[{"trad":"規則","simp":"规则","pinyin":"guī zé","defs":"rule; regulation / regular; orderly; fixed","hsk":"4","a":1,"pos":"名、形"}]],"sents":[[8,15,25],[24,34,67],[12],[46,55,65],[18],[3,11,17,23],[9],[4,6,30,35],[18],[13,22,29,43],[15,22],[30,42],[13],[5],[9],[15],[3,13],[10],[4,9],[7],[5,13,17,39],[12],[12],[29],[9],[16],[3,17,37],[14],[11],[52],[32],[1]]}