{"title":"臘葉","work":"野草","tokens":[[{"t":"燈","l":"2","s":"灯","d":0},{"t":"下","l":"1","d":1},{"t":"看","l":"1","d":2},{"t":"雁","d":3},{"t":"門","l":"1","s":"门","d":4},{"t":"集","l":"6","d":5},{"t":"，"},{"t":"忽然","l":"2","d":6},{"t":"翻","l":"4","d":7},{"t":"出","l":"1","d":8},{"t":"一","l":"1","d":9},{"t":"片","l":"2","d":10},{"t":"壓","l":"3","s":"压","d":11},{"t":"乾","l":"1","s":"干","d":12},{"t":"的","l":"1","d":13},{"t":"楓葉","s":"枫叶","d":14},{"t":"來","l":"1","s":"来","d":15},{"t":"。"}],[{"t":"這","l":"1","s":"这","d":16},{"t":"使","l":"3","d":17},{"t":"我","l":"1","d":18},{"t":"記起","s":"记起","d":19},{"t":"去年","l":"1","d":20},{"t":"的","l":"1","d":13},{"t":"深秋","d":21},{"t":"。"},{"t":"繁","d":22},{"t":"霜","l":"7-9","d":23},{"t":"夜","l":"2","d":24},{"t":"降","l":"4","d":25},{"t":"，"},{"t":"木","d":26},{"t":"葉","s":"叶","d":27},{"t":"多半","l":"6","d":28},{"t":"凋零","d":29},{"t":"，"},{"t":"庭","d":30},{"t":"前","l":"1","d":31},{"t":"的","l":"1","d":13},{"t":"一","l":"1","d":9},{"t":"株","l":"7-9","d":32},{"t":"小小","d":33},{"t":"的","l":"1","d":13},{"t":"楓樹","s":"枫树","d":34},{"t":"也","l":"1","d":35},{"t":"變成","l":"2","s":"变成","d":36},{"t":"紅色","l":"2","s":"红色","d":37},{"t":"了","l":"1","d":38},{"t":"。"},{"t":"我","l":"1","d":18},{"t":"曾","l":"4","d":39},{"t":"繞","l":"5","s":"绕","d":40},{"t":"樹","l":"1","s":"树","d":41},{"t":"徘徊","l":"7-9","d":42},{"t":"，"},{"t":"細看","s":"细看","d":43},{"t":"葉片","s":"叶片","d":44},{"t":"的","l":"1","d":13},{"t":"顏色","l":"2","s":"颜色","d":45},{"t":"，"},{"t":"當","l":"2","s":"当","d":46},{"t":"他","l":"1","d":47},{"t":"靑","d":48},{"t":"蔥","l":"7-9","s":"葱","d":49},{"t":"的","l":"1","d":13},{"t":"時候","l":"1","s":"时候","d":50},{"t":"是","l":"1","d":51},{"t":"從沒","l":"6","s":"从没","d":52},{"t":"有","l":"1","d":53},{"t":"這麽","s":"这么","d":54},{"t":"注意","l":"3","d":55},{"t":"的","l":"1","d":13},{"t":"。"},{"t":"他","l":"1","d":47},{"t":"也","l":"1","d":35},{"t":"並非","l":"7-9","s":"并非","d":56},{"t":"全","l":"2","d":57},{"t":"樹","l":"1","s":"树","d":41},{"t":"通紅","l":"6","s":"通红","d":58},{"t":"，"},{"t":"最多","d":59},{"t":"的","l":"1","d":13},{"t":"是","l":"1","d":51},{"t":"淺","l":"4","s":"浅","d":60},{"t":"絳","s":"绛","d":61},{"t":"，"},{"t":"有","l":"1","d":53},{"t":"幾","l":"1","s":"几","d":62},{"t":"片","l":"2","d":10},{"t":"則","l":"7-9","s":"则","d":63},{"t":"在","l":"1","d":64},{"t":"緋紅","s":"绯红","d":65},{"t":"地上","l":"1","d":66},{"t":"，"},{"t":"還","l":"1","s":"还","d":67},{"t":"帶","l":"2","s":"带","d":68},{"t":"着","l":"1","d":69},{"t":"幾","l":"1","s":"几","d":62},{"t":"團","l":"3","s":"团","d":70},{"t":"濃","l":"4","s":"浓","d":71},{"t":"綠","l":"2","s":"绿","d":72},{"t":"。"},{"t":"一","l":"1","d":9},{"t":"片","l":"2","d":10},{"t":"獨有","s":"独有","d":73},{"t":"一點","s":"一点","d":74},{"t":"蛀","d":75},{"t":"孔","d":76},{"t":"，"},{"t":"鑲","l":"7-9","s":"镶","d":77},{"t":"着","l":"1","d":69},{"t":"烏黑","s":"乌黑","d":78},{"t":"的","l":"1","d":13},{"t":"花邊","s":"花边","d":79},{"t":"，"},{"t":"在","l":"1","d":64},{"t":"紅","l":"2","s":"红","d":80},{"t":"、"},{"t":"黃","l":"2","s":"黄","d":81},{"t":"和","l":"1","d":82},{"t":"綠","l":"2","s":"绿","d":72},{"t":"的","l":"1","d":13},{"t":"斑駁","s":"斑驳","d":83},{"t":"中","l":"1","d":84},{"t":"，"},{"t":"明","d":85},{"t":"眸","d":86},{"t":"似的","l":"4","d":87},{"t":"向","l":"2","d":88},{"t":"人","l":"1","d":89},{"t":"凝視","s":"凝视","d":90},{"t":"。"},{"t":"我","l":"1","d":18},{"t":"自","l":"4","d":91},{"t":"念","l":"3","d":92},{"t":"："},{"t":"這","l":"1","s":"这","d":16},{"t":"是","l":"1","d":51},{"t":"病","l":"1","d":93},{"t":"葉","s":"叶","d":27},{"t":"呵","d":94},{"t":"！"},{"t":"便","l":"6","d":95},{"t":"將","l":"5","s":"将","d":96},{"t":"他","l":"1","d":47},{"t":"摘","l":"5","d":97},{"t":"了","l":"1","d":38},{"t":"下來","l":"3","s":"下来","d":98},{"t":"，"},{"t":"夾","l":"5","s":"夹","d":99},{"t":"在","l":"1","d":64},{"t":"剛纔","s":"刚才","d":100},{"t":"買","l":"1","s":"买","d":101},{"t":"到","l":"1","d":102},{"t":"的","l":"1","d":13},{"t":"雁","d":3},{"t":"門","l":"1","s":"门","d":4},{"t":"集","l":"6","d":5},{"t":"裏","l":"1","s":"里","d":103},{"t":"。"},{"t":"大概","l":"3","d":104},{"t":"是","l":"1","d":51},{"t":"願","l":"5","s":"愿","d":105},{"t":"使","l":"3","d":17},{"t":"這","l":"1","s":"这","d":16},{"t":"將","l":"5","s":"将","d":96},{"t":"墜","l":"7-9","s":"坠","d":106},{"t":"的","l":"1","d":13},{"t":"被","l":"3","d":107},{"t":"蝕","s":"蚀","d":108},{"t":"而","l":"4","d":109},{"t":"斑斕","s":"斑斓","d":110},{"t":"的","l":"1","d":13},{"t":"顏色","l":"2","s":"颜色","d":45},{"t":"，"},{"t":"暫","l":"7-9","s":"暂","d":111},{"t":"得","l":"2","d":112},{"t":"保存","l":"3","d":113},{"t":"，"},{"t":"不","l":"1","d":114},{"t":"卽","s":"即","d":115},{"t":"與","l":"6","s":"与","d":116},{"t":"羣","s":"群","d":117},{"t":"葉","s":"叶","d":27},{"t":"一同","l":"6","d":118},{"t":"飄散","s":"飘散","d":119},{"t":"罷","s":"罢","d":120},{"t":"。"}],[{"t":"但","l":"2","d":121},{"t":"今夜","d":122},{"t":"他","l":"1","d":47},{"t":"卻","l":"4","s":"却","d":123},{"t":"黃蠟","s":"黄蜡","d":124},{"t":"似的","l":"4","d":87},{"t":"躺","l":"4","d":125},{"t":"在","l":"1","d":64},{"t":"我","l":"1","d":18},{"t":"的","l":"1","d":13},{"t":"眼前","l":"3","d":126},{"t":"，"},{"t":"那","l":"1","d":127},{"t":"眸子","d":128},{"t":"也","l":"1","d":35},{"t":"不復","s":"不复","d":129},{"t":"似","d":130},{"t":"去年","l":"1","d":20},{"t":"一般","l":"2","d":131},{"t":"灼","d":132},{"t":"灼","d":132},{"t":"。"},{"t":"假使","l":"7-9","d":133},{"t":"再","l":"1","d":134},{"t":"過","l":"1","s":"过","d":135},{"t":"幾年","s":"几年","d":136},{"t":"，"},{"t":"舊時","s":"旧时","d":137},{"t":"的","l":"1","d":13},{"t":"顏色","l":"2","s":"颜色","d":45},{"t":"在","l":"1","d":64},{"t":"我","l":"1","d":18},{"t":"記憶","l":"5","s":"记忆","d":138},{"t":"中","l":"1","d":84},{"t":"消去","d":139},{"t":"，"},{"t":"怕","l":"2","d":140},{"t":"連","l":"3","s":"连","d":141},{"t":"我","l":"1","d":18},{"t":"也","l":"1","d":35},{"t":"不知","l":"7-9","d":142},{"t":"道","l":"2","d":143},{"t":"他","l":"1","d":47},{"t":"何以","d":144},{"t":"夾","l":"5","s":"夹","d":99},{"t":"在","l":"1","d":64},{"t":"書","l":"1","s":"书","d":145},{"t":"裏面","s":"里面","d":146},{"t":"的","l":"1","d":13},{"t":"原因","l":"2","d":147},{"t":"了","l":"1","d":38},{"t":"，"},{"t":"將","l":"5","s":"将","d":96},{"t":"墜","l":"7-9","s":"坠","d":106},{"t":"的","l":"1","d":13},{"t":"病","l":"1","d":93},{"t":"葉","s":"叶","d":27},{"t":"的","l":"1","d":13},{"t":"斑斕","s":"斑斓","d":110},{"t":"，"},{"t":"似乎","l":"4","d":148},{"t":"也","l":"1","d":35},{"t":"只能","l":"2","d":149},{"t":"在","l":"1","d":64},{"t":"極","l":"4","s":"极","d":150},{"t":"短","l":"2","d":151},{"t":"時","l":"3","s":"时","d":152},{"t":"中","l":"1","d":84},{"t":"相對","l":"7-9","s":"相对","d":153},{"t":"，"},{"t":"更","l":"2","d":154},{"t":"何況","l":"7-9","s":"何况","d":155},{"t":"是","l":"1","d":51},{"t":"蔥鬱","s":"葱郁","d":156},{"t":"的","l":"1","d":13},{"t":"呢","l":"1","d":157},{"t":"。"},{"t":"看看","d":158},{"t":"窗","d":159},{"t":"外","l":"1","d":160},{"t":"，"},{"t":"很","l":"1","d":161},{"t":"能耐","l":"7-9","d":162},{"t":"寒","d":163},{"t":"的","l":"1","d":13},{"t":"樹木","l":"7-9","s":"树木","d":164},{"t":"也","l":"1","d":35},{"t":"早","l":"1","d":165},{"t":"經","l":"7-9","s":"经","d":166},{"t":"禿","l":"7-9","s":"秃","d":167},{"t":"盡","l":"6","s":"尽","d":168},{"t":"了","l":"1","d":38},{"t":"；"},{"t":"楓樹","s":"枫树","d":34},{"t":"更","l":"2","d":154},{"t":"何","d":169},{"t":"消","l":"7-9","d":170},{"t":"說","l":"1","s":"说","d":171},{"t":"得","l":"2","d":112},{"t":"。"},{"t":"當","l":"2","s":"当","d":46},{"t":"深秋","d":21},{"t":"時","l":"3","s":"时","d":152},{"t":"，"},{"t":"想來","s":"想来","d":172},{"t":"也許","l":"2","s":"也许","d":173},{"t":"有","l":"1","d":53},{"t":"和","l":"1","d":82},{"t":"這","l":"1","s":"这","d":16},{"t":"去年","l":"1","d":20},{"t":"的","l":"1","d":13},{"t":"模樣","l":"5","s":"模样","d":174},{"t":"相似","l":"3","d":175},{"t":"的","l":"1","d":13},{"t":"病","l":"1","d":93},{"t":"葉","s":"叶","d":27},{"t":"的","l":"1","d":13},{"t":"罷","s":"罢","d":120},{"t":"，"},{"t":"但","l":"2","d":121},{"t":"可惜","l":"5","d":176},{"t":"我","l":"1","d":18},{"t":"今年","l":"1","d":177},{"t":"竟","l":"7-9","d":178},{"t":"沒有","l":"1","s":"没有","d":179},{"t":"賞","l":"4","s":"赏","d":180},{"t":"玩","d":181},{"t":"秋","d":182},{"t":"樹","l":"1","s":"树","d":41},{"t":"的","l":"1","d":13},{"t":"餘","l":"7-9","s":"余","d":183},{"t":"閒","l":"5","s":"闲","d":184},{"t":"。"}],[{"t":"（"},{"t":"一","l":"1","d":9},{"t":"九","l":"1","d":185},{"t":"二","l":"1","d":186},{"t":"五","l":"1","d":187},{"t":"年","l":"1","d":188},{"t":"十二月","d":189},{"t":"二十","d":190},{"t":"六","l":"1","d":191},{"t":"日","l":"1","d":192},{"t":"。）"}],[{"t":"1996"},{"t":"年","l":"1","d":188},{"t":"1"},{"t":"月","l":"1","d":193},{"t":"1"},{"t":"日","l":"1","d":192},{"t":"，"},{"t":"这","l":"1","d":194},{"t":"部","l":"3","d":195},{"t":"作品","l":"3","d":196},{"t":"在","l":"1","d":64},{"t":"原作","d":197},{"t":"國家","l":"1","s":"国家","d":198},{"t":"或","l":"2","d":199},{"t":"地區","l":"3","s":"地区","d":200},{"t":"屬於","l":"3","s":"属于","d":201},{"t":"公有","d":202},{"t":"領域","l":"7-9","s":"领域","d":203},{"t":"，"},{"t":"之前","l":"4","d":204},{"t":"在","l":"1","d":64},{"t":"美國","s":"美国","d":205},{"t":"從未","l":"7-9","s":"从未","d":206},{"t":"出版","l":"5","d":207},{"t":"，"},{"t":"其","l":"5","d":208},{"t":"作者","l":"3","d":209},{"t":"1936"},{"t":"年","l":"1","d":188},{"t":"逝世","l":"7-9","d":210},{"t":"，"},{"t":"在","l":"1","d":64},{"t":"美國","s":"美国","d":205},{"t":"以及","l":"4","d":211},{"t":"版權","s":"版权","d":212},{"t":"期限","l":"4","d":213},{"t":"是","l":"1","d":51},{"t":"作者","l":"3","d":209},{"t":"終身","l":"5","s":"终身","d":214},{"t":"加","l":"2","d":215},{"t":"80"},{"t":"年","l":"1","d":188},{"t":"以下","l":"2","d":216},{"t":"的","l":"1","d":13},{"t":"國家","l":"1","s":"国家","d":198},{"t":"以及","l":"4","d":211},{"t":"地区","l":"3","d":217},{"t":"，"},{"t":"屬於","l":"3","s":"属于","d":201},{"t":"公有","d":202},{"t":"領域","l":"7-9","s":"领域","d":203},{"t":"。"}],[{"t":"这","l":"1","d":194},{"t":"部","l":"3","d":195},{"t":"作品","l":"3","d":196},{"t":"也","l":"1","d":35},{"t":"可能","l":"2","d":218},{"t":"在","l":"1","d":64},{"t":"本國","s":"本国","d":219},{"t":"本地","l":"6","d":220},{"t":"版權","s":"版权","d":212},{"t":"期限","l":"4","d":213},{"t":"更","l":"2","d":154},{"t":"長","l":"2","s":"长","d":221},{"t":"，"},{"t":"但","l":"2","d":121},{"t":"對外","l":"6","s":"对外","d":222},{"t":"國外","l":"1","s":"国外","d":223},{"t":"地","l":"1","d":224},{"t":"作品","l":"3","d":196},{"t":"應用","l":"3","s":"应用","d":225},{"t":"較","l":"3","s":"较","d":226},{"t":"短期","l":"3","d":227},{"t":"限","l":"7-9","d":228},{"t":"規則","l":"4","s":"规则","d":229},{"t":"的","l":"1","d":13},{"t":"國家","l":"1","s":"国家","d":198},{"t":"以及","l":"4","d":211},{"t":"地区","l":"3","d":217},{"t":"，"},{"t":"屬於","l":"3","s":"属于","d":201},{"t":"公有","d":202},{"t":"領域","l":"7-9","s":"领域","d":203},{"t":"。"}],[{"t":"Public domainPublic domainfalsefalse"}]],"dict":[[{"trad":"燈","simp":"灯","pinyin":"dēng","defs":"lamp / light / lantern / CL:盞|盏[zhan3]","hsk":"2","a":1,"pos":"名"}],[{"trad":"下","simp":"下","pinyin":"xià","defs":"down / downwards / below / lower / later / next (week etc) / second (of two parts) / to decline / to go down / to arrive at (a decision, conclusion etc) / measure word to show the frequency of an action","hsk":"1","a":1,"pos":"名、动、量"}],[{"trad":"看","simp":"看","pinyin":"kān","defs":"to look after / to take care of / to watch / to guard","hsk":"1","a":1,"pos":"动"},{"trad":"看","simp":"看","pinyin":"kàn","defs":"to see; to look at / to read / to watch / to visit; to call on / to consider; to regard as / to look after / to treat (a patient or illness) / to depend on / to feel (that) / (after a verb) to give it a try / to watch out for","hsk":"1","a":1,"pos":"动"}],[{"trad":"雁","simp":"雁","pinyin":"yàn","defs":"wild goose","hsk":null},{"trad":"鴈","simp":"雁","pinyin":"yàn","defs":"variant of 雁[yan4]","hsk":null}],[{"trad":"門","simp":"门","pinyin":"Mén","defs":"surname Men","hsk":"1","a":1,"pos":"名"},{"trad":"門","simp":"门","pinyin":"mén","defs":"gate; door; doorway; gateway; opening (CL:扇[shan4]) / valve; switch; other door-like or gate-like structure / way to do sth; knack; method; approach / family; household; lineage / (bound form) sect; school; faction (religious or academic) / (bound form) class; category; division; phylum / classifier for courses, fields of study, branches of technology, relatives by marriage, guns etc / (suffix) -gate (scandal)","hsk":"1","a":1,"pos":"名"}],[{"trad":"集","simp":"集","pinyin":"jí","defs":"to gather / to collect / collected works / classifier for sections of a TV series etc: episode","hsk":"6","a":1,"pos":"名、量"}],[{"trad":"忽然","simp":"忽然","pinyin":"hū rán","defs":"suddenly; all of a sudden","hsk":"2","a":1,"pos":"副"}],[{"trad":"翻","simp":"翻","pinyin":"fān","defs":"to turn over / to flip over / to overturn / to rummage through / to translate / to decode / to double / to climb over or into / to cross","hsk":"4","a":1,"pos":"动"},{"trad":"飜","simp":"翻","pinyin":"fān","defs":"variant of 翻[fan1]","hsk":"4","a":1,"pos":"动"}],[{"trad":"出","simp":"出","pinyin":"chū","defs":"to go out; to come out / to arise; to occur / to produce; to yield / to go beyond; to exceed / (used after a verb to indicate an outward direction or a positive result) / classifier for dramas, plays, operas etc","hsk":"1","a":1,"pos":"动"},{"trad":"齣","simp":"出","pinyin":"chū","defs":"variant of 出[chu1] (classifier for plays or chapters of classical novels)","hsk":"1","a":1,"pos":"动"}],[{"trad":"一","simp":"一","pinyin":"yī","defs":"one / single / a (article) / as soon as / entire; whole; all; throughout / \"one\" radical in Chinese characters (Kangxi radical 1) / also pr. [yao1] for greater clarity when spelling out numbers digit by digit","hsk":"1","a":1,"pos":"数"}],[{"trad":"片","simp":"片","pinyin":"piān","defs":"disk / sheet","hsk":"2","a":1,"pos":"名、量"},{"trad":"片","simp":"片","pinyin":"piàn","defs":"thin piece / flake / a slice / film / TV play / to slice / to carve thin / partial / incomplete / one-sided / classifier for slices, tablets, tract of land, area of water / classifier for CDs, movies, DVDs etc / used with numeral 一[yi1]: classifier for scenario, scene, feeling, atmosphere, sound etc / Kangxi radical 91","hsk":"2","a":1,"pos":"名、量"}],[{"trad":"壓","simp":"压","pinyin":"yā","defs":"to press / to push down / to keep under (control) / pressure","hsk":"3","a":1,"pos":"动"},{"trad":"壓","simp":"压","pinyin":"yà","defs":"used in 壓根兒|压根儿[ya4 gen1 r5] / used in 壓馬路|压马路[ya4 ma3 lu4] / used in 壓板|压板[ya4 ban3]","hsk":"3","a":1,"pos":"动"}],[{"trad":"乾","simp":"乾","pinyin":"Qián","defs":"surname Qian","hsk":"1"},{"trad":"乾","simp":"乾","pinyin":"qián","defs":"one of the Eight Trigrams 八卦[ba1 gua4], symbolizing heaven / male principle / ☰ / ancient Chinese compass point: 315° (northwest)","hsk":"1"},{"trad":"乾","simp":"干","pinyin":"Gān","defs":"surname Gan","hsk":"1","a":1,"pos":"动、形、（名）"},{"trad":"乾","simp":"干","pinyin":"gān","defs":"dry / dried food / empty; hollow / taken in to nominal kinship; adoptive; foster / futile; in vain / (dialect) rude; blunt / (dialect) to cold-shoulder","hsk":"1","a":1,"pos":"动、形、（名）"},{"trad":"乹","simp":"乾","pinyin":"qián","defs":"old variant of 乾[qian2]","hsk":"1"},{"trad":"亁","simp":"乾","pinyin":"qián","defs":"variant of 乾[qian2]","hsk":"1"}],[{"trad":"的","simp":"的","pinyin":"de","defs":"of; ~'s (possessive particle) / (used after an attribute when it modifies a noun) / (used at the end of a declarative sentence for emphasis) / (used after a noun, verb or adjective to form a nominal expression, as in 皮革的[pi2 ge2 de5] \"one made of leather\" or 跑堂兒的|跑堂儿的[pao3 tang2 r5 de5] \"a waiter (literally, one who runs back and forth in a restaurant)\" or 新的[xin1 de5] \"new one\") / also pr. [di4] or [di5] in poetry and songs","hsk":"1","a":1,"pos":"助"},{"trad":"的","simp":"的","pinyin":"dī","defs":"a taxi; a cab (abbr. for 的士[di1 shi4])","hsk":"1","a":1,"pos":"助"},{"trad":"的","simp":"的","pinyin":"dí","defs":"really and truly","hsk":"1","a":1,"pos":"助"},{"trad":"的","simp":"的","pinyin":"dì","defs":"(bound form) bull's-eye; target","hsk":"1","a":1,"pos":"助"}],[{"trad":"楓葉","simp":"枫叶","pinyin":"fēng yè","defs":"maple leaf","hsk":null}],[{"trad":"來","simp":"来","pinyin":"lái","defs":"to come / (used as a substitute for a more specific verb) / hither (directional complement for motion toward the speaker, as in 回來|回来[hui2 lai5]) / ever since (as in 自古以來|自古以来[zi4 gu3 yi3 lai2]) / for the past (amount of time) / (prefix) the coming ...; the next ... (as in 來世|来世[lai2 shi4]) / (between two verbs) in order to / (after a round number) approximately / (used after 得[de2] to indicate possibility, as in 談得來|谈得来[tan2 de5 lai2], or after 不[bu4] to indicate impossibility, as in 吃不來|吃不来[chi1 bu5 lai2])","hsk":"1","a":1,"pos":"动"}],[{"trad":"這","simp":"这","pinyin":"zhè","defs":"(pronoun) this; these / (bound form) this; the (followed by a noun) / (bound form) this; these (followed by a classifier) (in this sense, commonly pr. [zhei4], esp. in Beijing)","hsk":"1","a":1,"pos":"代"},{"trad":"這","simp":"这","pinyin":"zhèi","defs":"(coll.) this","hsk":"1","a":1,"pos":"代"}],[{"trad":"使","simp":"使","pinyin":"shǐ","defs":"to make / to cause / to enable / to use / to employ / to send / to instruct sb to do sth / envoy / messenger","hsk":"3","a":1,"pos":"动"}],[{"trad":"我","simp":"我","pinyin":"wǒ","defs":"I; me; my","hsk":"1","a":1,"pos":"代"}],[{"trad":"記起","simp":"记起","pinyin":"jì qǐ","defs":"to recall / to recollect","hsk":null}],[{"trad":"去年","simp":"去年","pinyin":"qù nián","defs":"last year","hsk":"1","a":1,"pos":"名"}],[{"trad":"深秋","simp":"深秋","pinyin":"shēn qiū","defs":"late autumn","hsk":null}],[{"trad":"繁","simp":"繁","pinyin":"Pó","defs":"surname Po","hsk":null},{"trad":"繁","simp":"繁","pinyin":"fán","defs":"complicated / many / in great numbers / abbr. for 繁體|繁体[fan2 ti3], traditional form of Chinese characters","hsk":null},{"trad":"緐","simp":"繁","pinyin":"fán","defs":"old variant of 繁[fan2]","hsk":null}],[{"trad":"霜","simp":"霜","pinyin":"shuāng","defs":"frost / white powder or cream spread over a surface / frosting / (skin) cream","hsk":"7-9","a":1,"pos":"名"}],[{"trad":"夜","simp":"夜","pinyin":"yè","defs":"night","hsk":"2","a":1,"pos":"名、量"},{"trad":"亱","simp":"夜","pinyin":"yè","defs":"variant of 夜[ye4]","hsk":"2","a":1,"pos":"名、量"}],[{"trad":"降","simp":"降","pinyin":"jiàng","defs":"to drop / to fall / to come down / to descend","hsk":"4","a":1,"pos":"动"},{"trad":"降","simp":"降","pinyin":"xiáng","defs":"to surrender; to capitulate / to subdue; to conquer; to tame","hsk":"4","a":1,"pos":"动"}],[{"trad":"木","simp":"木","pinyin":"Mù","defs":"surname Mu","hsk":null},{"trad":"木","simp":"木","pinyin":"mù","defs":"(bound form) tree / (bound form) wood / unresponsive; numb; wooden","hsk":null}],[{"trad":"葉","simp":"叶","pinyin":"Yè","defs":"surname Ye","hsk":null},{"trad":"葉","simp":"叶","pinyin":"yè","defs":"leaf / page / lobe / (historical) period / classifier for small boats","hsk":null}],[{"trad":"多半","simp":"多半","pinyin":"duō bàn","defs":"most / mostly / most likely","hsk":"6","a":1,"pos":"数、副"}],[{"trad":"凋零","simp":"凋零","pinyin":"diāo líng","defs":"withered / wilted / to wither / to fade / to decay","hsk":null}],[{"trad":"庭","simp":"庭","pinyin":"tíng","defs":"main hall / front courtyard / law court","hsk":null}],[{"trad":"前","simp":"前","pinyin":"qián","defs":"front / forward / ahead / first / top (followed by a number) / future / ago / before / BC (e.g. 前293年) / former / formerly","hsk":"1","a":1,"pos":"名"}],[{"trad":"株","simp":"株","pinyin":"zhū","defs":"tree trunk / stump (tree root) / a plant / classifier for trees or plants / strain (biology) / to involve others (in shady business)","hsk":"7-9","a":1,"pos":"量"}],[{"trad":"小小","simp":"小小","pinyin":"xiǎo xiǎo","defs":"very small / very few / very minor","hsk":null}],[{"trad":"楓樹","simp":"枫树","pinyin":"fēng shù","defs":"maple","hsk":null}],[{"trad":"也","simp":"也","pinyin":"Yě","defs":"surname Ye","hsk":"1","a":1,"pos":"副"},{"trad":"也","simp":"也","pinyin":"yě","defs":"also; too; as well; (not ...) either / (used after a verbal or nominal expression X to indicate that X is an extreme or unexpected case) even (X) / (literary) particle having functions similar to 啊[a5]","hsk":"1","a":1,"pos":"副"}],[{"trad":"變成","simp":"变成","pinyin":"biàn chéng","defs":"to change into / to turn into / to become","hsk":"2","a":1,"pos":"动"}],[{"trad":"紅色","simp":"红色","pinyin":"hóng sè","defs":"red (color) / revolutionary","hsk":"2","a":1,"pos":"名"}],[{"trad":"了","simp":"了","pinyin":"le","defs":"(completed action marker) / (modal particle indicating change of state, situation now) / (modal particle intensifying preceding clause)","hsk":"1","a":1,"pos":"助"},{"trad":"了","simp":"了","pinyin":"liǎo","defs":"to finish / (used with 得[de2] or 不[bu4] after a verb to express (im)possibility, as in 忘不了[wang4 bu5 liao3] \"cannot forget\") / (literary) (usually followed by a negative such as 無|无[wu2] or 不[bu4]) completely (not); entirely (not); (not) in the least / to understand clearly (variant of 瞭|了[liao3])","hsk":"1","a":1,"pos":"助"},{"trad":"瞭","simp":"了","pinyin":"liǎo","defs":"(of eyes) bright / clear-sighted / to understand clearly","hsk":"1","a":1,"pos":"助"},{"trad":"瞭","simp":"了","pinyin":"liào","defs":"unofficial variant of 瞭[liao4]","hsk":"1","a":1,"pos":"助"}],[{"trad":"曾","simp":"曾","pinyin":"Zēng","defs":"surname Zeng","hsk":"4","a":1,"pos":"副"},{"trad":"曾","simp":"曾","pinyin":"céng","defs":"once / already / ever (in the past) / former / previously / (past tense marker used before verb or clause)","hsk":"4","a":1,"pos":"副"},{"trad":"曾","simp":"曾","pinyin":"zēng","defs":"great- (grandfather, grandchild etc)","hsk":"4","a":1,"pos":"副"}],[{"trad":"繞","simp":"绕","pinyin":"rào","defs":"to wind / to coil (thread) / to rotate around / to spiral / to move around / to go round (an obstacle) / to by-pass / to make a detour / to confuse / to perplex","hsk":"5","a":1,"pos":"动"}],[{"trad":"樹","simp":"树","pinyin":"shù","defs":"tree / CL:棵[ke1] / to cultivate / to set up","hsk":"1","a":1,"pos":"名"}],[{"trad":"徘徊","simp":"徘徊","pinyin":"pái huái","defs":"to pace back and forth / to dither; to hesitate / (of sales figures etc) to fluctuate","hsk":"7-9","a":1,"pos":"动"}],[{"trad":"細看","simp":"细看","pinyin":"xì kàn","defs":"to peer / to scan / to examine carefully","hsk":null}],[{"trad":"葉片","simp":"叶片","pinyin":"yè piàn","defs":"blade (of propellor) / vane / leaf","hsk":null}],[{"trad":"顏色","simp":"颜色","pinyin":"yán sè","defs":"color / countenance / appearance / facial expression / pigment / dyestuff","hsk":"2","a":1,"pos":"名"}],[{"trad":"當","simp":"当","pinyin":"dāng","defs":"to be / to act as / manage / withstand / when / during / ought / should / match equally / equal / same / obstruct / just at (a time or place) / on the spot / right / just at","hsk":"2","a":1,"pos":"动、介"},{"trad":"當","simp":"当","pinyin":"dàng","defs":"at or in the very same... / suitable / adequate / fitting / proper / to replace / to regard as / to think / to pawn / (coll.) to fail (a student)","hsk":"2","a":1,"pos":"动、介"}],[{"trad":"他","simp":"他","pinyin":"tā","defs":"(third-person singular) (since the early 20th century, usu. male) he; him; his / (bound form) other; another; some other (as in 他日[ta1 ri4] and 他人[ta1 ren2])","hsk":"1","a":1,"pos":"代"}],[{"trad":"靑","simp":"靑","pinyin":"qīng","defs":"variant of 青[qing1]","hsk":null}],[{"trad":"蔥","simp":"葱","pinyin":"cōng","defs":"scallion / green onion","hsk":"7-9","a":1,"pos":"名"}],[{"trad":"時候","simp":"时候","pinyin":"shí hou","defs":"time / length of time / moment / period","hsk":"1","a":1,"pos":"名"}],[{"trad":"是","simp":"是","pinyin":"shì","defs":"to be (followed by substantives only) / correct; right; true / (respectful acknowledgement of a command) very well / (adverb for emphatic assertion)","hsk":"1","a":1,"pos":"动"},{"trad":"昰","simp":"是","pinyin":"shì","defs":"variant of 是[shi4]","hsk":"1","a":1,"pos":"动"}],[{"trad":"從沒","simp":"从没","pinyin":"cóng méi","defs":"never (in the past) / never did","hsk":"6"}],[{"trad":"有","simp":"有","pinyin":"yǒu","defs":"to have; there is / (bound form) having; with; -ful; -ed; -al (as in 有意[you3 yi4] intentional)","hsk":"1","a":1,"pos":"动"}],[{"trad":"這麽","simp":"这么","pinyin":"zhè me","defs":"variant of 這麼|这么[zhe4 me5]","hsk":"2","a":1,"pos":"代"}],[{"trad":"注意","simp":"注意","pinyin":"zhù yì","defs":"to take note of; to pay attention to","hsk":"3","a":1,"pos":"动"}],[{"trad":"並非","simp":"并非","pinyin":"bìng fēi","defs":"really isn't","hsk":"7-9","a":1,"pos":"动"}],[{"trad":"全","simp":"全","pinyin":"Quán","defs":"surname Quan","hsk":"2","a":1,"pos":"形、副"},{"trad":"全","simp":"全","pinyin":"quán","defs":"all / whole / entire / every / complete","hsk":"2","a":1,"pos":"形、副"}],[{"trad":"通紅","simp":"通红","pinyin":"tōng hóng","defs":"very red / red through and through / to blush (deep red)","hsk":"6","a":1,"pos":"形"}],[{"trad":"最多","simp":"最多","pinyin":"zuì duō","defs":"at most / maximum / greatest (amount) / maximal","hsk":null}],[{"trad":"淺","simp":"浅","pinyin":"jiān","defs":"sound of moving water","hsk":"4","a":1,"pos":"形"},{"trad":"淺","simp":"浅","pinyin":"qiǎn","defs":"shallow / light (color)","hsk":"4","a":1,"pos":"形"}],[{"trad":"絳","simp":"绛","pinyin":"Jiàng","defs":"capital of the Jin State during the Spring and Autumn Period (770-475 BC)","hsk":null},{"trad":"絳","simp":"绛","pinyin":"jiàng","defs":"purple-red","hsk":null}],[{"trad":"幾","simp":"几","pinyin":"jī","defs":"(literary) almost","hsk":"1","a":1,"pos":"代、数"},{"trad":"幾","simp":"几","pinyin":"jǐ","defs":"how many; how much / several; a few","hsk":"1","a":1,"pos":"代、数"}],[{"trad":"則","simp":"则","pinyin":"zé","defs":"(literary) (conjunction used to express contrast with a previous clause) but; then / (bound form) standard; norm / (bound form) principle / (literary) to imitate; to follow / classifier for written items","hsk":"7-9","a":1,"pos":"连、（助）、量"}],[{"trad":"在","simp":"在","pinyin":"zài","defs":"to exist; to be alive / (of sb or sth) to be (located) at / (used before a verb to indicate an action in progress)","hsk":"1","a":1,"pos":"动、介、副"}],[{"trad":"緋紅","simp":"绯红","pinyin":"fēi hóng","defs":"crimson / scarlet","hsk":null}],[{"trad":"地上","simp":"地上","pinyin":"dì shang","defs":"on the ground / on the floor","hsk":"1"}],[{"trad":"還","simp":"还","pinyin":"Huán","defs":"surname Huan","hsk":"1","a":1,"pos":"副、动"},{"trad":"還","simp":"还","pinyin":"hái","defs":"still / still in progress / still more / yet / even more / in addition / fairly / passably (good) / as early as / even / also / else","hsk":"1","a":1,"pos":"副、动"},{"trad":"還","simp":"还","pinyin":"huán","defs":"to pay back / to return","hsk":"1","a":1,"pos":"副、动"}],[{"trad":"帶","simp":"带","pinyin":"dài","defs":"band / belt / girdle / ribbon / tire / area / zone / region / CL:條|条[tiao2] / to wear / to carry / to take along / to bear (i.e. to have) / to lead / to bring / to look after / to raise","hsk":"2","a":1,"pos":"动、（名）"}],[{"trad":"着","simp":"着","pinyin":"zhāo","defs":"variant of 著|着[zhao1]","hsk":"1","a":1,"pos":"助、动"},{"trad":"着","simp":"着","pinyin":"zháo","defs":"variant of 著|着[zhao2]","hsk":"1","a":1,"pos":"助、动"},{"trad":"着","simp":"着","pinyin":"zhe","defs":"variant of 著|着[zhe5]","hsk":"1","a":1,"pos":"助、动"},{"trad":"着","simp":"着","pinyin":"zhuó","defs":"variant of 著|着[zhuo2]","hsk":"1","a":1,"pos":"助、动"},{"trad":"著","simp":"着","pinyin":"zhāo","defs":"a move in chess (Taiwan pr. [zhuo2]) / trick; tactic / (dialect) okay; all right / (dialect) to put in; to add","hsk":"1","a":1,"pos":"助、动"},{"trad":"著","simp":"着","pinyin":"zháo","defs":"to touch / to come in contact with / to feel / to be affected by / to catch fire / to burn / (coll.) to fall asleep / (after a verb) hitting the mark / succeeding in","hsk":"1","a":1,"pos":"助、动"},{"trad":"著","simp":"着","pinyin":"zhe","defs":"aspect particle indicating action in progress or ongoing state","hsk":"1","a":1,"pos":"助、动"},{"trad":"著","simp":"着","pinyin":"zhuó","defs":"to wear (clothes) / to contact / to use / to apply","hsk":"1","a":1,"pos":"助、动"}],[{"trad":"團","simp":"团","pinyin":"tuán","defs":"round / lump / ball / to roll into a ball / to gather / regiment / group / society / classifier for a lump or a soft mass: wad (of paper), ball (of wool), cloud (of smoke)","hsk":"3","a":1,"pos":"动、名、量"}],[{"trad":"濃","simp":"浓","pinyin":"nóng","defs":"concentrated / dense / strong (smell etc)","hsk":"4","a":1,"pos":"形"}],[{"trad":"綠","simp":"绿","pinyin":"lù","defs":"used in names","hsk":"2"},{"trad":"綠","simp":"绿","pinyin":"lǜ","defs":"green / (slang) (derived from 綠帽子|绿帽子[lu:4 mao4 zi5]) to cheat on (one's spouse or boyfriend or girlfriend)","hsk":"2"}],[{"trad":"獨有","simp":"独有","pinyin":"dú yǒu","defs":"to own exclusively; unique to; specific / there is only","hsk":null}],[{"trad":"一點","simp":"一点","pinyin":"yī diǎn","defs":"a bit; a little bit / (used in negative expressions) (not) the least bit / (after an adjective, used to form the comparative) a bit more, -er / a point (in a discussion etc) / (calligraphy) dot stroke (、) / one o'clock (abbr. for 一點鍾|一点钟[yi1 dian3 zhong1])","hsk":null}],[{"trad":"蛀","simp":"蛀","pinyin":"zhù","defs":"termite / to bore (of insects)","hsk":null}],[{"trad":"孔","simp":"孔","pinyin":"Kǒng","defs":"surname Kong","hsk":null,"a":1,"pos":"名"},{"trad":"孔","simp":"孔","pinyin":"kǒng","defs":"hole / CL:個|个[ge4] / classifier for cave dwellings","hsk":null,"a":1,"pos":"名"}],[{"trad":"鑲","simp":"镶","pinyin":"xiāng","defs":"to inlay / to embed / ridge / border","hsk":"7-9","a":1,"pos":"动"}],[{"trad":"烏黑","simp":"乌黑","pinyin":"wū hēi","defs":"jet-black / dark","hsk":null}],[{"trad":"花邊","simp":"花边","pinyin":"huā biān","defs":"lace / decorative border","hsk":null}],[{"trad":"紅","simp":"红","pinyin":"Hóng","defs":"surname Hong","hsk":"2","a":1,"pos":"形"},{"trad":"紅","simp":"红","pinyin":"gōng","defs":"used in 女紅|女红[nu : 3 gong1]","hsk":"2","a":1,"pos":"形"},{"trad":"紅","simp":"红","pinyin":"hóng","defs":"red / popular / revolutionary / bonus","hsk":"2","a":1,"pos":"形"}],[{"trad":"黃","simp":"黄","pinyin":"Huáng","defs":"surname Huang or Hwang","hsk":"2","a":1,"pos":"名"},{"trad":"黃","simp":"黄","pinyin":"huáng","defs":"yellow / pornographic / to fall through","hsk":"2","a":1,"pos":"名"}],[{"trad":"和","simp":"和","pinyin":"Hé","defs":"surname He","hsk":"1","a":1,"pos":"介、连、形"},{"trad":"和","simp":"和","pinyin":"hé","defs":"(joining two nouns) and; together with; with (Taiwan pr. [han4]) / (math.) sum / to make peace / (sports) to draw; to tie / (bound form) harmonious / (bound form) Japan; Japanese","hsk":"1","a":1,"pos":"介、连、形"},{"trad":"和","simp":"和","pinyin":"hè","defs":"to compose a poem in reply (to sb's poem) using the same rhyme sequence / to join in the singing / to chime in with others","hsk":"1","a":1,"pos":"介、连、形"},{"trad":"和","simp":"和","pinyin":"hú","defs":"to complete a set in mahjong or playing cards","hsk":"1","a":1,"pos":"介、连、形"},{"trad":"和","simp":"和","pinyin":"huó","defs":"to combine a powdery substance (flour, plaster etc) with water / Taiwan pr. [huo4]","hsk":"1","a":1,"pos":"介、连、形"},{"trad":"和","simp":"和","pinyin":"huò","defs":"to mix (ingredients) together / to blend / classifier for rinses of clothes / classifier for boilings of medicinal herbs","hsk":"1","a":1,"pos":"介、连、形"},{"trad":"咊","simp":"和","pinyin":"hé","defs":"old variant of 和[he2]","hsk":"1","a":1,"pos":"介、连、形"},{"trad":"龢","simp":"和","pinyin":"hé","defs":"(literary) harmonious (variant of 和[he2])","hsk":"1","a":1,"pos":"介、连、形"}],[{"trad":"斑駁","simp":"斑驳","pinyin":"bān bó","defs":"mottled / motley","hsk":null}],[{"trad":"中","simp":"中","pinyin":"Zhōng","defs":"(bound form) China; Chinese / surname Zhong","hsk":"1","a":1,"pos":"名、动"},{"trad":"中","simp":"中","pinyin":"zhōng","defs":"within; among; in / middle; center / while (doing sth); during / (dialect) OK; all right","hsk":"1","a":1,"pos":"名、动"},{"trad":"中","simp":"中","pinyin":"zhòng","defs":"to hit (a target) / to be struck by (a bullet, illness etc) / to win (a prize or lottery)","hsk":"1","a":1,"pos":"名、动"}],[{"trad":"明","simp":"明","pinyin":"Míng","defs":"Ming Dynasty (1368–1644) / surname Ming / Ming (c. 2000 BC), fourth of the legendary Flame Emperors, 炎帝[Yan2 di4] descended from Shennong 神農|神农[Shen2 nong2] Farmer God","hsk":null},{"trad":"明","simp":"明","pinyin":"míng","defs":"bright / opposite: dark 暗[an4] / (of meaning) clear / to understand / next / public or open / wise / generic term for a sacrifice to the gods","hsk":null}],[{"trad":"眸","simp":"眸","pinyin":"móu","defs":"pupil (of the eye) / eye","hsk":null}],[{"trad":"似的","simp":"似的","pinyin":"shì de","defs":"seems as if / rather like / Taiwan pr. [si4 de5]","hsk":"4","a":1,"pos":"助"}],[{"trad":"向","simp":"向","pinyin":"Xiàng","defs":"surname Xiang","hsk":"2","a":1,"pos":"动、介"},{"trad":"向","simp":"向","pinyin":"xiàng","defs":"towards / to face / to turn towards / direction / to support / to side with / shortly before / formerly / always / all along / (suffix) suitable for ... / oriented to ...","hsk":"2","a":1,"pos":"动、介"},{"trad":"嚮","simp":"向","pinyin":"xiàng","defs":"to tend toward / to guide / variant of 向[xiang4]","hsk":"2","a":1,"pos":"动、介"},{"trad":"曏","simp":"向","pinyin":"xiàng","defs":"variant of 向[xiang4] / direction / orientation / to face / to turn toward / to / towards / shortly before / formerly","hsk":"2","a":1,"pos":"动、介"}],[{"trad":"人","simp":"人","pinyin":"rén","defs":"person; people / CL:個|个[ge4],位[wei4],名[ming2]","hsk":"1","a":1,"pos":"名"}],[{"trad":"凝視","simp":"凝视","pinyin":"níng shì","defs":"to gaze at / to fix one's eyes on","hsk":null,"a":1,"pos":"动"}],[{"trad":"自","simp":"自","pinyin":"zì","defs":"(bound form) self; oneself / from; since / naturally; as a matter of course","hsk":"4","a":1,"pos":"介"}],[{"trad":"念","simp":"念","pinyin":"niàn","defs":"to read / to study (a subject) / to attend (a school) / to read aloud / to give (sb) a tongue-lashing (CL:頓|顿[dun4]) / to miss (sb) / idea / remembrance / twenty (banker's anti-fraud numeral corresponding to 廿[nian4])","hsk":"3","a":1,"pos":"动"},{"trad":"唸","simp":"念","pinyin":"niàn","defs":"variant of 念[nian4], to read aloud","hsk":"3","a":1,"pos":"动"}],[{"trad":"病","simp":"病","pinyin":"bìng","defs":"illness / CL:場|场[chang2] / disease / to fall ill / defect","hsk":"1","a":1,"pos":"名、动"}],[{"trad":"呵","simp":"呵","pinyin":"ā","defs":"variant of 啊[a1]","hsk":null,"a":1,"pos":"动"},{"trad":"呵","simp":"呵","pinyin":"hē","defs":"(bound form) to scold / to expel breath / (onom.) laughter (usu. reduplicated) / interjection of surprise","hsk":null,"a":1,"pos":"动"}],[{"trad":"便","simp":"便","pinyin":"biàn","defs":"plain / informal / suitable / convenient / opportune / to urinate or defecate / equivalent to 就[jiu4]: then / in that case / even if / soon afterwards","hsk":"6","a":1,"pos":"副"},{"trad":"便","simp":"便","pinyin":"pián","defs":"used in 便宜[pian2 yi5] / used in 便便[pian2 pian2] / used in 便嬛[pian2 xuan1]","hsk":"6","a":1,"pos":"副"}],[{"trad":"將","simp":"将","pinyin":"jiāng","defs":"will / shall / to use / to take / to checkmate / just a short while ago / (introduces object of main verb, used in the same way as 把[ba3])","hsk":"5","a":1,"pos":"介、副"},{"trad":"將","simp":"将","pinyin":"jiàng","defs":"(bound form) a general / (literary) to command; to lead / (Chinese chess) general (on the black side, equivalent to a king in Western chess)","hsk":"5","a":1,"pos":"介、副"},{"trad":"將","simp":"将","pinyin":"qiāng","defs":"to desire / to invite / to request","hsk":"5","a":1,"pos":"介、副"}],[{"trad":"摘","simp":"摘","pinyin":"zhāi","defs":"to take; to pick (flowers, fruit etc); to pluck; to remove; to take off (glasses, hat etc) / to select; to pick out / to borrow money at a time of urgent need","hsk":"5","a":1,"pos":"动"}],[{"trad":"下來","simp":"下来","pinyin":"xià lai","defs":"to come down / (completed action marker) / (after verb of motion, indicates motion down and towards us, also fig.) / (indicates continuation from the past towards us) / to be harvested (of crops) / to be over (of a period of time) / to go among the masses (said of leaders)","hsk":"3","a":1,"pos":"动"}],[{"trad":"夾","simp":"夹","pinyin":"gā","defs":"used in 夾肢窩|夹肢窝[ga1 zhi5 wo1]","hsk":"5","a":1,"pos":"动"},{"trad":"夾","simp":"夹","pinyin":"jiā","defs":"to press from either side / to place in between / to sandwich / to carry sth under armpit / wedged between / between / to intersperse / to mix / to mingle / clip / folder / Taiwan pr. [jia2]","hsk":"5","a":1,"pos":"动"},{"trad":"夾","simp":"夹","pinyin":"jiá","defs":"double-layered (quilt); lined (garment)","hsk":"5","a":1,"pos":"动"}],[{"trad":"剛纔","simp":"刚才","pinyin":"gāng cái","defs":"just now (variant of 剛才|刚才[gang1 cai2])","hsk":"2","a":1,"pos":"名"}],[{"trad":"買","simp":"买","pinyin":"mǎi","defs":"to buy / to purchase","hsk":"1","a":1,"pos":"动"}],[{"trad":"到","simp":"到","pinyin":"dào","defs":"to reach; to arrive / to leave for; to go to / to (a place); until (a time); up to (a point) / (verb complement indicating arriving at a place or reaching a point) / considerate; thoughtful; thorough","hsk":"1","a":1,"pos":"动"}],[{"trad":"裏","simp":"里","pinyin":"lǐ","defs":"variant of 裡|里[li3]","hsk":"1","a":1,"pos":"名"}],[{"trad":"大概","simp":"大概","pinyin":"dà gài","defs":"roughly / probably / rough / approximate / about / general idea","hsk":"3","a":1,"pos":"形、副、（名）"}],[{"trad":"願","simp":"愿","pinyin":"yuàn","defs":"(bound form) wish; hope; desire / to be willing / to wish (that sth may happen); may ... / vow; pledge","hsk":"5","a":1,"pos":"动"}],[{"trad":"墜","simp":"坠","pinyin":"zhuì","defs":"to fall / to drop / to weigh down","hsk":"7-9","a":1,"pos":"动、名"}],[{"trad":"被","simp":"被","pinyin":"bèi","defs":"quilt / to cover (with) / (literary) to suffer (a misfortune) / used to indicate passive voice (placed before the doer of the action like \"by\" in English passive-voice sentences, or, if the doer is not mentioned, before the verb) / (since c. 2009) (sarcastic or jocular) used to indicate that the following word should be regarded as being in air quotes (as in 被旅遊|被旅游[bei4 lu : 3 you2] to \"go on a trip\")","hsk":"3","a":1,"pos":"介"}],[{"trad":"蝕","simp":"蚀","pinyin":"shí","defs":"to nibble away at sth / to eat into / to erode","hsk":null}],[{"trad":"而","simp":"而","pinyin":"ér","defs":"and / as well as / and so / but (not) / yet (not) / (indicates causal relation) / (indicates change of state) / (indicates contrast)","hsk":"4","a":1,"pos":"连"}],[{"trad":"斑斕","simp":"斑斓","pinyin":"bān lán","defs":"gorgeous; brightly colored; multicolored","hsk":null}],[{"trad":"暫","simp":"暂","pinyin":"zàn","defs":"temporary / Taiwan pr. [zhan4]","hsk":"7-9","a":1,"pos":"副"}],[{"trad":"得","simp":"得","pinyin":"dé","defs":"to obtain / to get / to gain / to catch (a disease) / proper / suitable / proud / contented / to allow / to permit / ready / finished","hsk":"2","a":1,"pos":"助、动"},{"trad":"得","simp":"得","pinyin":"dè","defs":"used in 得瑟[de4 se5]","hsk":"2","a":1,"pos":"助、动"},{"trad":"得","simp":"得","pinyin":"de","defs":"structural particle: used after a verb (or adjective as main verb), linking it to following phrase indicating effect, degree, possibility etc","hsk":"2","a":1,"pos":"助、动"},{"trad":"得","simp":"得","pinyin":"děi","defs":"to have to / must / ought to / to need to","hsk":"2","a":1,"pos":"助、动"}],[{"trad":"保存","simp":"保存","pinyin":"bǎo cún","defs":"to conserve; to preserve; to keep; to store; (computing) to save (a file etc)","hsk":"3","a":1,"pos":"动"}],[{"trad":"不","simp":"不","pinyin":"bù","defs":"no; not so / (bound form) not; un-","hsk":"1","a":1,"pos":"副"}],[{"trad":"卽","simp":"卽","pinyin":"jí","defs":"variant of 即[ji2] / promptly","hsk":null}],[{"trad":"與","simp":"与","pinyin":"yú","defs":"variant of 歟|欤[yu2]","hsk":"6","a":1,"pos":"介、连"},{"trad":"與","simp":"与","pinyin":"yǔ","defs":"(formal) and; together with (linking parallel nouns, verbs, or phrases) / (formal) with; from (marking the other participant in an interaction, comparison, or contrast, e.g. 與他握手|与他握手[yu3 ta1 wo4 shou3] \"shake hands with him\", 與去年不同|与去年不同[yu3 qu4 nian2 bu4 tong2] \"different from last year\") / (literary) to give; to grant; to bestow","hsk":"6","a":1,"pos":"介、连"},{"trad":"與","simp":"与","pinyin":"yù","defs":"to take part in","hsk":"6","a":1,"pos":"介、连"}],[{"trad":"羣","simp":"群","pinyin":"qún","defs":"variant of 群[qun2]","hsk":"3","a":1,"pos":"量、名"}],[{"trad":"一同","simp":"一同","pinyin":"yī tóng","defs":"together","hsk":"6","a":1,"pos":"副"}],[{"trad":"飄散","simp":"飘散","pinyin":"piāo sàn","defs":"to waft (through the air); to drift","hsk":null}],[{"trad":"罷","simp":"罢","pinyin":"bà","defs":"to stop / to cease / to dismiss / to suspend / to quit / to finish","hsk":null},{"trad":"罷","simp":"罢","pinyin":"ba","defs":"(final particle, same as 吧)","hsk":null}],[{"trad":"但","simp":"但","pinyin":"dàn","defs":"but; yet; however; still / merely; only; just","hsk":"2","a":1,"pos":"连、（副）"}],[{"trad":"今夜","simp":"今夜","pinyin":"jīn yè","defs":"tonight / this evening","hsk":null}],[{"trad":"卻","simp":"却","pinyin":"què","defs":"but / yet / however / while / to go back / to decline / to retreat / nevertheless / even though","hsk":"4","a":1,"pos":"副"}],[{"trad":"黃蠟","simp":"黄蜡","pinyin":"huáng là","defs":"beeswax","hsk":null}],[{"trad":"躺","simp":"躺","pinyin":"tǎng","defs":"to recline / to lie down","hsk":"4","a":1,"pos":"动"}],[{"trad":"眼前","simp":"眼前","pinyin":"yǎn qián","defs":"before one's eyes / now / at present","hsk":"3","a":1,"pos":"名"}],[{"trad":"那","simp":"那","pinyin":"Nā","defs":"surname Na","hsk":"1","a":1,"pos":"代、（连）"},{"trad":"那","simp":"那","pinyin":"Nuó","defs":"surname Nuo","hsk":"1","a":1,"pos":"代、（连）"},{"trad":"那","simp":"那","pinyin":"nǎ","defs":"variant of 哪[na3]","hsk":"1","a":1,"pos":"代、（连）"},{"trad":"那","simp":"那","pinyin":"nà","defs":"(specifier) that; the; those (colloquial pr. [nei4]) / (pronoun) that (referring to persons, things or situations) / then (in that case)","hsk":"1","a":1,"pos":"代、（连）"},{"trad":"那","simp":"那","pinyin":"nuó","defs":"(archaic) many / beautiful / how / old variant of 挪[nuo2]","hsk":"1","a":1,"pos":"代、（连）"}],[{"trad":"眸子","simp":"眸子","pinyin":"móu zi","defs":"pupil of the eye","hsk":null}],[{"trad":"不復","simp":"不复","pinyin":"bù fù","defs":"no longer; not again","hsk":null}],[{"trad":"似","simp":"似","pinyin":"shì","defs":"used in 似的[shi4 de5]","hsk":null},{"trad":"似","simp":"似","pinyin":"sì","defs":"to seem / to appear / to resemble / similar / -like / pseudo- / (more) than","hsk":null},{"trad":"佀","simp":"似","pinyin":"sì","defs":"old variant of 似[si4]","hsk":null}],[{"trad":"一般","simp":"一般","pinyin":"yī bān","defs":"same / ordinary / so-so / common / general / generally / in general","hsk":"2","a":1,"pos":"形"}],[{"trad":"灼","simp":"灼","pinyin":"zhuó","defs":"to burn; to sear; to scorch / (bound form) bright; luminous","hsk":null}],[{"trad":"假使","simp":"假使","pinyin":"jiǎ shǐ","defs":"if / in case / suppose / given ...","hsk":"7-9","a":1,"pos":"连"}],[{"trad":"再","simp":"再","pinyin":"zài","defs":"again; once more; re- / further; beyond this point of time / (before an adjective) more / then (after sth, and not until then) / no matter how ... (followed by an adjective or verb, and then (usually) 也[ye3] or 都[dou1] for emphasis) / (used to introduce additional information, as in 再則|再则[zai4 ze2], 再就是[zai4 jiu4 shi4] etc) / (literary) to reappear; to reoccur","hsk":"1","a":1,"pos":"副"}],[{"trad":"過","simp":"过","pinyin":"Guō","defs":"surname Guo","hsk":"1","a":1,"pos":"动"},{"trad":"過","simp":"过","pinyin":"guò","defs":"to cross / to go over / to pass (time) / to celebrate (a holiday) / to live / to get along / excessively / too-","hsk":"1","a":1,"pos":"动"},{"trad":"過","simp":"过","pinyin":"guo","defs":"(experienced action marker)","hsk":"1","a":1,"pos":"动"}],[{"trad":"幾年","simp":"几年","pinyin":"jǐ nián","defs":"a few years; several years / how many years?","hsk":null}],[{"trad":"舊時","simp":"旧时","pinyin":"jiù shí","defs":"in former times / the olden days","hsk":null}],[{"trad":"記憶","simp":"记忆","pinyin":"jì yì","defs":"to remember; to recall / memory","hsk":"5","a":1,"pos":"动、名"}],[{"trad":"消去","simp":"消去","pinyin":"xiāo qù","defs":"to eliminate","hsk":null}],[{"trad":"怕","simp":"怕","pinyin":"Pà","defs":"surname Pa","hsk":"2","a":1,"pos":"动、（副）"},{"trad":"怕","simp":"怕","pinyin":"pà","defs":"to be afraid / to fear / to dread / to be unable to endure / perhaps","hsk":"2","a":1,"pos":"动、（副）"}],[{"trad":"連","simp":"连","pinyin":"Lián","defs":"surname Lian","hsk":"3","a":1,"pos":"介、（动、副）"},{"trad":"連","simp":"连","pinyin":"lián","defs":"to link / to join / to connect / continuously / in succession / including / (used with 也[ye3], 都[dou1] etc) even / company (military)","hsk":"3","a":1,"pos":"介、（动、副）"}],[{"trad":"不知","simp":"不知","pinyin":"bù zhī","defs":"not to know / unaware / unknowingly / fig. not to admit (defeat, hardships, tiredness etc)","hsk":"7-9"}],[{"trad":"道","simp":"道","pinyin":"dào","defs":"road; path (CL:條|条[tiao2],股[gu3]) / (bound form) way; reason; principle / (bound form) a skill; an art; a specialization / (Daoism) the Way; the Dao / to say (introducing a direct quotation, as in a novel) / (bound form) to express; to extend (polite words) / classifier for long thin things (rivers, cracks, shadows etc), barriers (walls, doors etc), questions (in an exam etc), commands, courses in a meal, steps in a process / (old) circuit (administrative division)","hsk":"2","a":1,"pos":"名、量"}],[{"trad":"何以","simp":"何以","pinyin":"hé yǐ","defs":"(literary) why / how","hsk":null}],[{"trad":"書","simp":"书","pinyin":"Shū","defs":"abbr. for 書經|书经[Shu1 jing1]","hsk":"1","a":1,"pos":"名"},{"trad":"書","simp":"书","pinyin":"shū","defs":"book / letter / document / CL:本[ben3],冊|册[ce4],部[bu4] / to write","hsk":"1","a":1,"pos":"名"}],[{"trad":"裏面","simp":"里面","pinyin":"lǐ miàn","defs":"variant of 裡面|里面[li3 mian4]","hsk":"3","a":1,"pos":"名"}],[{"trad":"原因","simp":"原因","pinyin":"yuán yīn","defs":"cause / origin / root cause / reason / CL:個|个[ge4]","hsk":"2","a":1,"pos":"名"}],[{"trad":"似乎","simp":"似乎","pinyin":"sì hū","defs":"it seems; seemingly; as if","hsk":"4","a":1,"pos":"副"}],[{"trad":"只能","simp":"只能","pinyin":"zhǐ néng","defs":"can only / obliged to do sth / to have no other choice","hsk":"2","a":1}],[{"trad":"極","simp":"极","pinyin":"jí","defs":"extremely / pole (geography, physics) / utmost / top","hsk":"4","a":1,"pos":"副"}],[{"trad":"短","simp":"短","pinyin":"duǎn","defs":"short / brief / to lack / weak point / fault","hsk":"2","a":1,"pos":"形"}],[{"trad":"時","simp":"时","pinyin":"Shí","defs":"surname Shi","hsk":"3","a":1,"pos":"名、（量）"},{"trad":"時","simp":"时","pinyin":"shí","defs":"o'clock / time / when / hour / season / period","hsk":"3","a":1,"pos":"名、（量）"}],[{"trad":"相對","simp":"相对","pinyin":"xiāng duì","defs":"relatively / opposite / to resist / to oppose / relative / vis-a-vis / counterpart","hsk":"7-9","a":1,"pos":"动、形"}],[{"trad":"更","simp":"更","pinyin":"gēng","defs":"to change or replace / to experience / one of the five two-hour periods into which the night was formerly divided / watch (e.g. of a sentry or guard)","hsk":"2","a":1,"pos":"副"},{"trad":"更","simp":"更","pinyin":"gèng","defs":"more / even more / further / still / still more","hsk":"2","a":1,"pos":"副"}],[{"trad":"何況","simp":"何况","pinyin":"hé kuàng","defs":"let alone / to say nothing of / besides / what's more","hsk":"7-9","a":1,"pos":"连"}],[{"trad":"蔥鬱","simp":"葱郁","pinyin":"cōng yù","defs":"verdant / lush green and full of life","hsk":null}],[{"trad":"呢","simp":"呢","pinyin":"ne","defs":"(sentence-final particle) used in questions to link back to prior discourse or context (\"what about...?\", \"and...?\") / (sentence-final particle) indicating that a state or situation still holds / (discourse particle) used to mark a slight pause or emphasis in speech","hsk":"1","a":1,"pos":"助"},{"trad":"呢","simp":"呢","pinyin":"ní","defs":"dense wool fabric (used for coats and jackets)","hsk":"1","a":1,"pos":"助"}],[{"trad":"看看","simp":"看看","pinyin":"kàn kan","defs":"to take a look at / to examine / to survey / (coll.) pretty soon","hsk":null}],[{"trad":"窗","simp":"窗","pinyin":"chuāng","defs":"window / CL:扇[shan4]","hsk":null,"a":1,"pos":"名"},{"trad":"牎","simp":"窗","pinyin":"chuāng","defs":"old variant of 窗[chuang1]","hsk":null,"a":1,"pos":"名"},{"trad":"牕","simp":"窗","pinyin":"chuāng","defs":"variant of 窗[chuang1]","hsk":null,"a":1,"pos":"名"},{"trad":"窓","simp":"窗","pinyin":"chuāng","defs":"variant of 窗[chuang1]","hsk":null,"a":1,"pos":"名"},{"trad":"窻","simp":"窗","pinyin":"chuāng","defs":"variant of 窗[chuang1]","hsk":null,"a":1,"pos":"名"}],[{"trad":"外","simp":"外","pinyin":"wài","defs":"outside / in addition / foreign / external","hsk":"1","a":1,"pos":"名"}],[{"trad":"很","simp":"很","pinyin":"hěn","defs":"very; quite / (also, often used before an adjective without intensifying its meaning, i.e. as a meaningless syntactic element)","hsk":"1","a":1,"pos":"副"}],[{"trad":"能耐","simp":"能耐","pinyin":"néng nài","defs":"ability / capability","hsk":"7-9","a":1,"pos":"名、形"}],[{"trad":"寒","simp":"寒","pinyin":"hán","defs":"cold / poor / to tremble","hsk":null}],[{"trad":"樹木","simp":"树木","pinyin":"shù mù","defs":"tree","hsk":"7-9","a":1,"pos":"名"}],[{"trad":"早","simp":"早","pinyin":"zǎo","defs":"early / morning / Good morning! / long ago / prematurely","hsk":"1","a":1,"pos":"形"}],[{"trad":"經","simp":"经","pinyin":"Jīng","defs":"surname Jing","hsk":"7-9","a":1,"pos":"动"},{"trad":"經","simp":"经","pinyin":"jīng","defs":"classics / sacred book / scripture / to pass through / to undergo / to bear / to endure / warp (textile) / longitude / menstruation / channel (TCM) / abbr. for economics 經濟|经济[jing1 ji4]","hsk":"7-9","a":1,"pos":"动"}],[{"trad":"禿","simp":"秃","pinyin":"tū","defs":"bald (lacking hair or feathers) / barren; bare; denuded / blunt (lacking a point) / (of a piece of writing) unsatisfactory; lacking something","hsk":"7-9","a":1,"pos":"形"}],[{"trad":"盡","simp":"尽","pinyin":"jìn","defs":"to use up / to exhaust / to end / to finish / to the utmost / exhausted / finished / to the limit (of sth) / all / entirely","hsk":"6","a":1,"pos":"动、（副）、副"}],[{"trad":"何","simp":"何","pinyin":"Hé","defs":"surname He","hsk":null,"a":1,"pos":"代"},{"trad":"何","simp":"何","pinyin":"hé","defs":"what / how / why / which / carry","hsk":null,"a":1,"pos":"代"}],[{"trad":"消","simp":"消","pinyin":"xiāo","defs":"to diminish; to subside / to consume; to reduce / to idle away (the time) / (after 不[bu4] or 只[zhi3] or 何[he2] etc) to need; to require; to take","hsk":"7-9","a":1,"pos":"动"}],[{"trad":"說","simp":"说","pinyin":"shuì","defs":"to persuade","hsk":"1","a":1,"pos":"动"},{"trad":"說","simp":"说","pinyin":"shuō","defs":"to speak; to talk; to say / to explain; to comment / to scold; to tell off / (bound form) theory; doctrine","hsk":"1","a":1,"pos":"动"}],[{"trad":"想來","simp":"想来","pinyin":"xiǎng lái","defs":"it may be assumed that","hsk":null}],[{"trad":"也許","simp":"也许","pinyin":"yě xǔ","defs":"perhaps; maybe","hsk":"2","a":1,"pos":"副"}],[{"trad":"模樣","simp":"模样","pinyin":"mú yàng","defs":"look / style / appearance / approximation / about / CL:個|个[ge4] / also pr. [mo2 yang4]","hsk":"5","a":1,"pos":"名"}],[{"trad":"相似","simp":"相似","pinyin":"xiāng sì","defs":"similar; alike","hsk":"3","a":1,"pos":"形"}],[{"trad":"可惜","simp":"可惜","pinyin":"kě xī","defs":"it is a pity / what a pity / unfortunately","hsk":"5","a":1,"pos":"形"}],[{"trad":"今年","simp":"今年","pinyin":"jīn nián","defs":"this year","hsk":"1","a":1,"pos":"名"}],[{"trad":"竟","simp":"竟","pinyin":"jìng","defs":"unexpectedly / actually / to go so far as to / indeed","hsk":"7-9","a":1,"pos":"副"}],[{"trad":"沒有","simp":"没有","pinyin":"méi yǒu","defs":"haven't / hasn't / doesn't exist / to not have / to not be","hsk":"1","a":1,"pos":"动、副"}],[{"trad":"賞","simp":"赏","pinyin":"shǎng","defs":"to bestow (a reward) / to give (to an inferior) / to hand down / a reward (bestowed by a superior) / to appreciate (beauty)","hsk":"4","a":1,"pos":"动"}],[{"trad":"玩","simp":"玩","pinyin":"wán","defs":"to play / to have fun / to trifle with / toy / sth used for amusement / curio or antique (Taiwan pr. [wan4]) / to keep sth for entertainment","hsk":null,"a":1,"pos":"动"},{"trad":"翫","simp":"玩","pinyin":"wán","defs":"variant of 玩[wan2] / Taiwan pr. [wan4]","hsk":null,"a":1,"pos":"动"}],[{"trad":"秋","simp":"秋","pinyin":"Qiū","defs":"surname Qiu","hsk":null},{"trad":"秋","simp":"秋","pinyin":"qiū","defs":"autumn / fall / harvest time","hsk":null},{"trad":"秌","simp":"秋","pinyin":"qiū","defs":"old variant of 秋[qiu1]","hsk":null},{"trad":"鞦","simp":"秋","pinyin":"qiū","defs":"used in 鞦韆|秋千[qiu1 qian1]","hsk":null}],[{"trad":"餘","simp":"余","pinyin":"yú","defs":"extra / surplus / remaining / remainder after division / (following numerical value) or more / in excess of (some number) / residue (math.) / after / I / me","hsk":"7-9","a":1,"pos":"动、数"},{"trad":"餘","simp":"馀","pinyin":"Yú","defs":"surname Yu","hsk":"7-9"},{"trad":"餘","simp":"馀","pinyin":"yú","defs":"variant of 餘|余[yu2], remainder","hsk":"7-9"}],[{"trad":"閒","simp":"閒","pinyin":"jiān","defs":"variant of 間|间[jian1]","hsk":"5"},{"trad":"閒","simp":"閒","pinyin":"jiàn","defs":"variant of 間|间[jian4]","hsk":"5"},{"trad":"閒","simp":"闲","pinyin":"xián","defs":"idle / unoccupied / leisure","hsk":"5","a":1,"pos":"形"}],[{"trad":"九","simp":"九","pinyin":"jiǔ","defs":"nine / 9","hsk":"1","a":1,"pos":"数"}],[{"trad":"二","simp":"二","pinyin":"èr","defs":"two / 2 / (Beijing dialect) stupid","hsk":"1","a":1,"pos":"数"}],[{"trad":"五","simp":"五","pinyin":"wǔ","defs":"five / 5","hsk":"1","a":1,"pos":"数"}],[{"trad":"年","simp":"年","pinyin":"Nián","defs":"surname Nian","hsk":"1","a":1,"pos":"名、量"},{"trad":"年","simp":"年","pinyin":"nián","defs":"year / CL:個|个[ge4]","hsk":"1","a":1,"pos":"名、量"},{"trad":"秊","simp":"年","pinyin":"nián","defs":"grain / harvest (old) / variant of 年[nian2]","hsk":"1","a":1,"pos":"名、量"}],[{"trad":"十二月","simp":"十二月","pinyin":"Shí èr yuè","defs":"December / twelfth month (of the lunar year)","hsk":null}],[{"trad":"二十","simp":"二十","pinyin":"èr shí","defs":"twenty; 20","hsk":null}],[{"trad":"六","simp":"六","pinyin":"liù","defs":"six / 6","hsk":"1","a":1,"pos":"数"},{"trad":"六","simp":"六","pinyin":"lù","defs":"used in place names","hsk":"1","a":1,"pos":"数"}],[{"trad":"日","simp":"日","pinyin":"rì","defs":"(bound form) sun / day / day of the month / (bound form) Japan (abbr. for 日本[Ri4 ben3]) / (vulgar) to fuck; to have sex with","hsk":"1","a":1,"pos":"量、（名）"}],[{"trad":"月","simp":"月","pinyin":"yuè","defs":"moon / month / monthly / CL:個|个[ge4],輪|轮[lun2]","hsk":"1","a":1,"pos":"名"}],[{"trad":"這","simp":"这","pinyin":"zhè","defs":"(pronoun) this; these / (bound form) this; the (followed by a noun) / (bound form) this; these (followed by a classifier) (in this sense, commonly pr. [zhei4], esp. in Beijing)","hsk":"1","a":1,"pos":"代"},{"trad":"這","simp":"这","pinyin":"zhèi","defs":"(coll.) this","hsk":"1","a":1,"pos":"代"}],[{"trad":"部","simp":"部","pinyin":"bù","defs":"ministry / department / section / part / division / troops / board / classifier for works of literature, films, machines etc","hsk":"3","a":1,"pos":"名、量"}],[{"trad":"作品","simp":"作品","pinyin":"zuò pǐn","defs":"work (of art) / opus / CL:部[bu4],篇[pian1]","hsk":"3","a":1,"pos":"名"}],[{"trad":"原作","simp":"原作","pinyin":"yuán zuò","defs":"original works / original text / original author","hsk":null}],[{"trad":"國家","simp":"国家","pinyin":"guó jiā","defs":"country; nation; state","hsk":"1","a":1,"pos":"名"}],[{"trad":"或","simp":"或","pinyin":"huò","defs":"maybe / perhaps / might / possibly / or","hsk":"2","a":1,"pos":"连、（副）"}],[{"trad":"地區","simp":"地区","pinyin":"dì qū","defs":"region; area (informal or geographical term) / prefecture (in China's administrative system)","hsk":"3","a":1,"pos":"名"}],[{"trad":"屬於","simp":"属于","pinyin":"shǔ yú","defs":"to belong to; to fall under (a category)","hsk":"3","a":1,"pos":"动"}],[{"trad":"公有","simp":"公有","pinyin":"gōng yǒu","defs":"publicly owned / communal / held in common","hsk":null}],[{"trad":"領域","simp":"领域","pinyin":"lǐng yù","defs":"domain; sphere; field; territory; area","hsk":"7-9","a":1,"pos":"名"}],[{"trad":"之前","simp":"之前","pinyin":"zhī qián","defs":"before / prior to / ago / previously / beforehand","hsk":"4","a":1,"pos":"名"}],[{"trad":"美國","simp":"美国","pinyin":"Měi guó","defs":"United States; USA; US","hsk":null}],[{"trad":"從未","simp":"从未","pinyin":"cóng wèi","defs":"never","hsk":"7-9","a":1,"pos":"副"}],[{"trad":"出版","simp":"出版","pinyin":"chū bǎn","defs":"to publish","hsk":"5","a":1,"pos":"动"}],[{"trad":"其","simp":"其","pinyin":"qí","defs":"his / her / its / their / that / such / it (refers to sth preceding it)","hsk":"5","a":1,"pos":"代"}],[{"trad":"作者","simp":"作者","pinyin":"zuò zhě","defs":"author; writer","hsk":"3","a":1,"pos":"名"}],[{"trad":"逝世","simp":"逝世","pinyin":"shì shì","defs":"to pass away / to die","hsk":"7-9","a":1,"pos":"动"}],[{"trad":"以及","simp":"以及","pinyin":"yǐ jí","defs":"and; as well as","hsk":"4","a":1,"pos":"连"}],[{"trad":"版權","simp":"版权","pinyin":"bǎn quán","defs":"copyright","hsk":null,"a":1,"pos":"名"}],[{"trad":"期限","simp":"期限","pinyin":"qī xiàn","defs":"time limit / deadline / allotted time","hsk":"4","a":1,"pos":"名"}],[{"trad":"終身","simp":"终身","pinyin":"zhōng shēn","defs":"lifelong / all one's life / marriage","hsk":"5","a":1,"pos":"名"}],[{"trad":"加","simp":"加","pinyin":"Jiā","defs":"Canada (abbr. for 加拿大[Jia1 na2 da4]) / surname Jia","hsk":"2","a":1,"pos":"动"},{"trad":"加","simp":"加","pinyin":"jiā","defs":"to add / (math.) plus / to increase; to augment / (used before a disyllabic verb, often after an adverb like 不[bu4], 大[da4], 稍[shao1] etc, to indicate that the action applies to sth previously mentioned, as in 稍加改良[shao1 jia1 gai3 liang2] \"make some minor improvements to (it)\")","hsk":"2","a":1,"pos":"动"}],[{"trad":"以下","simp":"以下","pinyin":"yǐ xià","defs":"that level or lower / that amount or less / the following","hsk":"2","a":1,"pos":"名"}],[{"trad":"地區","simp":"地区","pinyin":"dì qū","defs":"region; area (informal or geographical term) / prefecture (in China's administrative system)","hsk":"3","a":1,"pos":"名"}],[{"trad":"可能","simp":"可能","pinyin":"kě néng","defs":"might (happen) / possible / probable / possibility / probability / maybe / perhaps / CL:個|个[ge4]","hsk":"2","a":1,"pos":"形、名、动"}],[{"trad":"本國","simp":"本国","pinyin":"běn guó","defs":"one's own country","hsk":null}],[{"trad":"本地","simp":"本地","pinyin":"běn dì","defs":"local / this locality","hsk":"6","a":1,"pos":"名"}],[{"trad":"長","simp":"长","pinyin":"cháng","defs":"long / (bound form) length / (bound form) strong point; forte / (bound form) to be good at / (literary) surplus; spare (Taiwan pr. [zhang4])","hsk":"2","a":1,"pos":"形、动、后缀"},{"trad":"長","simp":"长","pinyin":"zhǎng","defs":"chief / head / elder / to grow / to develop / to increase / to enhance","hsk":"2","a":1,"pos":"形、动、后缀"}],[{"trad":"對外","simp":"对外","pinyin":"duì wài","defs":"external / foreign / pertaining to external or foreign (affairs)","hsk":"6"}],[{"trad":"國外","simp":"国外","pinyin":"guó wài","defs":"abroad / external (affairs) / overseas / foreign","hsk":"1"}],[{"trad":"地","simp":"地","pinyin":"de","defs":"-ly / structural particle: used before a verb or adjective, linking it to preceding modifying adverbial adjunct","hsk":"1","a":1,"pos":"助、名"},{"trad":"地","simp":"地","pinyin":"dì","defs":"earth / ground / field / place / land / CL:片[pian4]","hsk":"1","a":1,"pos":"助、名"}],[{"trad":"應用","simp":"应用","pinyin":"yìng yòng","defs":"to put to use; to apply / practical; applied (science, linguistics etc) / application; practical use / (computing) app","hsk":"3","a":1,"pos":"动、形"}],[{"trad":"較","simp":"较","pinyin":"jiào","defs":"(bound form) to compare / (literary) to dispute / compared to / (before an adjective) relatively; comparatively; rather / also pr. [jiao3]","hsk":"3","a":1,"pos":"介、副"}],[{"trad":"短期","simp":"短期","pinyin":"duǎn qī","defs":"short-term","hsk":"3","a":1,"pos":"名、形"}],[{"trad":"限","simp":"限","pinyin":"xiàn","defs":"to limit / to restrict / (bound form) limit / bound","hsk":"7-9","a":1,"pos":"动"}],[{"trad":"規則","simp":"规则","pinyin":"guī zé","defs":"rule; regulation / regular; orderly; fixed","hsk":"4","a":1,"pos":"名、形"}]],"sents":[[18],[8,31,55,84,114,124,142,170],[22,77,93,100,133],[11],[52],[32],[1]]}